{
"meta":{"test_sets":[],"test_metrics":[],"learn_metrics":[{"best_value":"Min","name":"RMSE"}],"launch_mode":"Train","parameters":"","iteration_count":1000,"learn_sets":["learn"],"name":"experiment"},
"iterations":[
{"learn":[1.469875746],"iteration":0,"passed_time":0.1523877332,"remaining_time":152.2353454},
{"learn":[1.444676172],"iteration":1,"passed_time":0.1557740178,"remaining_time":77.7312349},
{"learn":[1.422222845],"iteration":2,"passed_time":0.1587766383,"remaining_time":52.76676946},
{"learn":[1.3993443],"iteration":3,"passed_time":0.1634172106,"remaining_time":40.69088544},
{"learn":[1.376868837],"iteration":4,"passed_time":0.1677692168,"remaining_time":33.38607415},
{"learn":[1.355066104],"iteration":5,"passed_time":0.1740127051,"remaining_time":28.82810481},
{"learn":[1.334644554],"iteration":6,"passed_time":0.1821863102,"remaining_time":25.84442943},
{"learn":[1.316304897],"iteration":7,"passed_time":0.1898999888,"remaining_time":23.54759862},
{"learn":[1.300590309],"iteration":8,"passed_time":0.1953941578,"remaining_time":21.51506782},
{"learn":[1.283101566],"iteration":9,"passed_time":0.2022586173,"remaining_time":20.02360311},
{"learn":[1.265932334],"iteration":10,"passed_time":0.2072582476,"remaining_time":18.63440063},
{"learn":[1.250473582],"iteration":11,"passed_time":0.2105665835,"remaining_time":17.33664871},
{"learn":[1.23707752],"iteration":12,"passed_time":0.2139090232,"remaining_time":16.24063123},
{"learn":[1.222788415],"iteration":13,"passed_time":0.2188203907,"remaining_time":15.41120752},
{"learn":[1.208836105],"iteration":14,"passed_time":0.222297045,"remaining_time":14.59750595},
{"learn":[1.195126056],"iteration":15,"passed_time":0.2256841853,"remaining_time":13.8795774},
{"learn":[1.181193716],"iteration":16,"passed_time":0.228524814,"remaining_time":13.21411131},
{"learn":[1.167606393],"iteration":17,"passed_time":0.2307913636,"remaining_time":12.59095106},
{"learn":[1.156453526],"iteration":18,"passed_time":0.2399674017,"remaining_time":12.38989584},
{"learn":[1.146884642],"iteration":19,"passed_time":0.2426332781,"remaining_time":11.88903063},
{"learn":[1.135701],"iteration":20,"passed_time":0.2452714481,"remaining_time":11.43432132},
{"learn":[1.125087817],"iteration":21,"passed_time":0.2489933278,"remaining_time":11.06888521},
{"learn":[1.114545635],"iteration":22,"passed_time":0.2525350151,"remaining_time":10.72724825},
{"learn":[1.105406832],"iteration":23,"passed_time":0.2556088273,"remaining_time":10.39475898},
{"learn":[1.096137202],"iteration":24,"passed_time":0.2582492589,"remaining_time":10.0717211},
{"learn":[1.087470103],"iteration":25,"passed_time":0.2608089395,"remaining_time":9.770304118},
{"learn":[1.079477599],"iteration":26,"passed_time":0.2641559655,"remaining_time":9.519398314},
{"learn":[1.070844721],"iteration":27,"passed_time":0.2680283967,"remaining_time":9.304414343},
{"learn":[1.062791532],"iteration":28,"passed_time":0.2711953258,"remaining_time":9.080367631},
{"learn":[1.054874076],"iteration":29,"passed_time":0.2743189742,"remaining_time":8.869646833},
{"learn":[1.047743522],"iteration":30,"passed_time":0.2777241984,"remaining_time":8.68112091},
{"learn":[1.041020643],"iteration":31,"passed_time":0.2800779171,"remaining_time":8.472356993},
{"learn":[1.035315069],"iteration":32,"passed_time":0.2832504159,"remaining_time":8.300095521},
{"learn":[1.027852624],"iteration":33,"passed_time":0.2859706227,"remaining_time":8.124930044},
{"learn":[1.021301883],"iteration":34,"passed_time":0.2888314454,"remaining_time":7.963495565},
{"learn":[1.015689],"iteration":35,"passed_time":0.2911847192,"remaining_time":7.797279703},
{"learn":[1.009560136],"iteration":36,"passed_time":0.2938946327,"remaining_time":7.649203549},
{"learn":[1.003938152],"iteration":37,"passed_time":0.2961030291,"remaining_time":7.496081948},
{"learn":[0.9987430427],"iteration":38,"passed_time":0.2987012169,"remaining_time":7.360304344},
{"learn":[0.9921887521],"iteration":39,"passed_time":0.3007886851,"remaining_time":7.218928443},
{"learn":[0.9860837638],"iteration":40,"passed_time":0.3030742655,"remaining_time":7.088980991},
{"learn":[0.9805483695],"iteration":41,"passed_time":0.3057291912,"remaining_time":6.973537265},
{"learn":[0.9758074246],"iteration":42,"passed_time":0.3077356844,"remaining_time":6.848908138},
{"learn":[0.9701234748],"iteration":43,"passed_time":0.310320437,"remaining_time":6.742416767},
{"learn":[0.9650164112],"iteration":44,"passed_time":0.3126644123,"remaining_time":6.63543364},
{"learn":[0.9589495638],"iteration":45,"passed_time":0.3155635087,"remaining_time":6.544512767},
{"learn":[0.9541385738],"iteration":46,"passed_time":0.3182978824,"remaining_time":6.453997488},
{"learn":[0.950070067],"iteration":47,"passed_time":0.3207200432,"remaining_time":6.360947524},
{"learn":[0.9458260224],"iteration":48,"passed_time":0.3232177799,"remaining_time":6.273063443},
{"learn":[0.9415283007],"iteration":49,"passed_time":0.32659602,"remaining_time":6.205324379},
{"learn":[0.9378873076],"iteration":50,"passed_time":0.3291465474,"remaining_time":6.124707324},
{"learn":[0.9342750711],"iteration":51,"passed_time":0.3314496962,"remaining_time":6.042582924},
{"learn":[0.9300169716],"iteration":52,"passed_time":0.3344505579,"remaining_time":5.975937326},
{"learn":[0.9259884821],"iteration":53,"passed_time":0.3369647509,"remaining_time":5.90312323},
{"learn":[0.9220801865],"iteration":54,"passed_time":0.3398294111,"remaining_time":5.838887154},
{"learn":[0.9177879991],"iteration":55,"passed_time":0.3423650065,"remaining_time":5.771295824},
{"learn":[0.9143538056],"iteration":56,"passed_time":0.3447733548,"remaining_time":5.703881993},
{"learn":[0.9104780733],"iteration":57,"passed_time":0.3468977825,"remaining_time":5.634098467},
{"learn":[0.9081880365],"iteration":58,"passed_time":0.3488089817,"remaining_time":5.563207657},
{"learn":[0.9044074261],"iteration":59,"passed_time":0.3511887631,"remaining_time":5.501957288},
{"learn":[0.901193728],"iteration":60,"passed_time":0.3534410651,"remaining_time":5.440674756},
{"learn":[0.8966426381],"iteration":61,"passed_time":0.3556908543,"remaining_time":5.381258409},
{"learn":[0.8942268817],"iteration":62,"passed_time":0.3581887023,"remaining_time":5.327346254},
{"learn":[0.8905031124],"iteration":63,"passed_time":0.3603019965,"remaining_time":5.269416698},
{"learn":[0.8878760938],"iteration":64,"passed_time":0.36279614,"remaining_time":5.218682937},
{"learn":[0.8854070311],"iteration":65,"passed_time":0.3655895413,"remaining_time":5.173645933},
{"learn":[0.8828053464],"iteration":66,"passed_time":0.367638029,"remaining_time":5.119496732},
{"learn":[0.8792634229],"iteration":67,"passed_time":0.3698098509,"remaining_time":5.068570309},
{"learn":[0.8766499876],"iteration":68,"passed_time":0.3717516984,"remaining_time":5.015954076},
{"learn":[0.8741337917],"iteration":69,"passed_time":0.3738137562,"remaining_time":4.966382761},
{"learn":[0.870336587],"iteration":70,"passed_time":0.3760290018,"remaining_time":4.920154122},
{"learn":[0.868394756],"iteration":71,"passed_time":0.3780998165,"remaining_time":4.873286523},
{"learn":[0.8665620105],"iteration":72,"passed_time":0.3803792261,"remaining_time":4.830295104},
{"learn":[0.8641300968],"iteration":73,"passed_time":0.3828600909,"remaining_time":4.790924921},
{"learn":[0.861914469],"iteration":74,"passed_time":0.3855414435,"remaining_time":4.755011137},
{"learn":[0.85911006],"iteration":75,"passed_time":0.3878751054,"remaining_time":4.715744703},
{"learn":[0.8578219418],"iteration":76,"passed_time":0.3900775061,"remaining_time":4.675864132},
{"learn":[0.8547194412],"iteration":77,"passed_time":0.3920898241,"remaining_time":4.634702792},
{"learn":[0.8520355356],"iteration":78,"passed_time":0.3949812142,"remaining_time":4.604780991},
{"learn":[0.8500738953],"iteration":79,"passed_time":0.3971122342,"remaining_time":4.566790693},
{"learn":[0.8468011512],"iteration":80,"passed_time":0.3990764498,"remaining_time":4.5277933},
{"learn":[0.8450886501],"iteration":81,"passed_time":0.4013968077,"remaining_time":4.493686213},
{"learn":[0.8419844171],"iteration":82,"passed_time":0.4043808628,"remaining_time":4.467677725},
{"learn":[0.8396900701],"iteration":83,"passed_time":0.406242652,"remaining_time":4.429979396},
{"learn":[0.8382320752],"iteration":84,"passed_time":0.4085931299,"remaining_time":4.398384869},
{"learn":[0.8357682889],"iteration":85,"passed_time":0.4105332186,"remaining_time":4.363108859},
{"learn":[0.8342073781],"iteration":86,"passed_time":0.4129625178,"remaining_time":4.333733089},
{"learn":[0.8325558028],"iteration":87,"passed_time":0.4152627363,"remaining_time":4.303631995},
{"learn":[0.8305708249],"iteration":88,"passed_time":0.4173753527,"remaining_time":4.272235352},
{"learn":[0.8287418995],"iteration":89,"passed_time":0.4198108712,"remaining_time":4.244754365},
{"learn":[0.826969588],"iteration":90,"passed_time":0.4218968944,"remaining_time":4.214332715},
{"learn":[0.8254029881],"iteration":91,"passed_time":0.4243621468,"remaining_time":4.188269884},
{"learn":[0.8237335105],"iteration":92,"passed_time":0.4268927066,"remaining_time":4.16335145},
{"learn":[0.8217401638],"iteration":93,"passed_time":0.42883415,"remaining_time":4.133231275},
{"learn":[0.819992427],"iteration":94,"passed_time":0.4313591217,"remaining_time":4.109263212},
{"learn":[0.8178980394],"iteration":95,"passed_time":0.4340253109,"remaining_time":4.087071678},
{"learn":[0.8149242919],"iteration":96,"passed_time":0.4359705975,"remaining_time":4.058571644},
{"learn":[0.8133519457],"iteration":97,"passed_time":0.4384332157,"remaining_time":4.035375108},
{"learn":[0.8123255428],"iteration":98,"passed_time":0.4407404248,"remaining_time":4.011183058},
{"learn":[0.8112440349],"iteration":99,"passed_time":0.4438847883,"remaining_time":3.994963095},
{"learn":[0.8101207307],"iteration":100,"passed_time":0.4452654797,"remaining_time":3.963303626},
{"learn":[0.8090239256],"iteration":101,"passed_time":0.4478980117,"remaining_time":3.943258966},
{"learn":[0.8074308601],"iteration":102,"passed_time":0.450637522,"remaining_time":3.92448405},
{"learn":[0.8059893295],"iteration":103,"passed_time":0.4526393574,"remaining_time":3.899662156},
{"learn":[0.804880704],"iteration":104,"passed_time":0.4547446228,"remaining_time":3.876156547},
{"learn":[0.803017506],"iteration":105,"passed_time":0.457107088,"remaining_time":3.855223931},
{"learn":[0.8017190723],"iteration":106,"passed_time":0.4590090857,"remaining_time":3.830795454},
{"learn":[0.799951579],"iteration":107,"passed_time":0.4615804717,"remaining_time":3.812312785},
{"learn":[0.7990343312],"iteration":108,"passed_time":0.463820381,"remaining_time":3.791412472},
{"learn":[0.7971612609],"iteration":109,"passed_time":0.4658653953,"remaining_time":3.769274562},
{"learn":[0.795453362],"iteration":110,"passed_time":0.4679923711,"remaining_time":3.748155117},
{"learn":[0.7945107026],"iteration":111,"passed_time":0.4701285734,"remaining_time":3.727447975},
{"learn":[0.793333808],"iteration":112,"passed_time":0.4724882231,"remaining_time":3.708823486},
{"learn":[0.7912862327],"iteration":113,"passed_time":0.4750192119,"remaining_time":3.691815981},
{"learn":[0.7897639014],"iteration":114,"passed_time":0.4770437753,"remaining_time":3.671162967},
{"learn":[0.7887367723],"iteration":115,"passed_time":0.4793803593,"remaining_time":3.653208945},
{"learn":[0.7878434023],"iteration":116,"passed_time":0.4814285436,"remaining_time":3.633345333},
{"learn":[0.7873910223],"iteration":117,"passed_time":0.4835036457,"remaining_time":3.613984877},
{"learn":[0.7856200631],"iteration":118,"passed_time":0.4854765773,"remaining_time":3.594158526},
{"learn":[0.7843714872],"iteration":119,"passed_time":0.4874605515,"remaining_time":3.574710711},
{"learn":[0.7835470089],"iteration":120,"passed_time":0.4895249192,"remaining_time":3.55613557},
{"learn":[0.7826011934],"iteration":121,"passed_time":0.4916738567,"remaining_time":3.538439723},
{"learn":[0.7815055944],"iteration":122,"passed_time":0.493803891,"remaining_time":3.52086189},
{"learn":[0.7800205133],"iteration":123,"passed_time":0.4962513968,"remaining_time":3.505775997},
{"learn":[0.7792449319],"iteration":124,"passed_time":0.4981387153,"remaining_time":3.486971007},
{"learn":[0.7786477946],"iteration":125,"passed_time":0.5000018024,"remaining_time":3.46826647},
{"learn":[0.7774364129],"iteration":126,"passed_time":0.5022879791,"remaining_time":3.452735478},
{"learn":[0.7762188931],"iteration":127,"passed_time":0.50421835,"remaining_time":3.434987509},
{"learn":[0.7753253541],"iteration":128,"passed_time":0.5062184471,"remaining_time":3.417955562},
{"learn":[0.7735621381],"iteration":129,"passed_time":0.5082594767,"remaining_time":3.401428806},
{"learn":[0.7722270457],"iteration":130,"passed_time":0.5105582831,"remaining_time":3.386833191},
{"learn":[0.7704331131],"iteration":131,"passed_time":0.5128179263,"remaining_time":3.372166364},
{"learn":[0.7692652865],"iteration":132,"passed_time":0.5147977037,"remaining_time":3.355861723},
{"learn":[0.768371563],"iteration":133,"passed_time":0.5167396767,"remaining_time":3.339526568},
{"learn":[0.7674359442],"iteration":134,"passed_time":0.5189101433,"remaining_time":3.324868696},
{"learn":[0.7665649387],"iteration":135,"passed_time":0.5221418122,"remaining_time":3.317136219},
{"learn":[0.7654943701],"iteration":136,"passed_time":0.524923995,"remaining_time":3.306638013},
{"learn":[0.763861924],"iteration":137,"passed_time":0.5270510619,"remaining_time":3.292159531},
{"learn":[0.763440543],"iteration":138,"passed_time":0.5294681235,"remaining_time":3.279655067},
{"learn":[0.7623253083],"iteration":139,"passed_time":0.5321654256,"remaining_time":3.269016186},
{"learn":[0.7615870925],"iteration":140,"passed_time":0.5347215712,"remaining_time":3.257629997},
{"learn":[0.7607080033],"iteration":141,"passed_time":0.5369177929,"remaining_time":3.244193425},
{"learn":[0.7589362377],"iteration":142,"passed_time":0.5392769092,"remaining_time":3.231890288},
{"learn":[0.7573303225],"iteration":143,"passed_time":0.541983051,"remaining_time":3.221788136},
{"learn":[0.756338561],"iteration":144,"passed_time":0.5441472384,"remaining_time":3.208592337},
{"learn":[0.7558241851],"iteration":145,"passed_time":0.5465314595,"remaining_time":3.196834702},
{"learn":[0.755055133],"iteration":146,"passed_time":0.5497845914,"remaining_time":3.190246643},
{"learn":[0.7542999152],"iteration":147,"passed_time":0.5522085038,"remaining_time":3.178930035},
{"learn":[0.7536445164],"iteration":148,"passed_time":0.5546186868,"remaining_time":3.167654379},
{"learn":[0.7531489721],"iteration":149,"passed_time":0.5562652644,"remaining_time":3.152169831},
{"learn":[0.7526104783],"iteration":150,"passed_time":0.5593750811,"remaining_time":3.145095655},
{"learn":[0.75253477],"iteration":151,"passed_time":0.5600129413,"remaining_time":3.124282725},
{"learn":[0.7521517877],"iteration":152,"passed_time":0.5620226753,"remaining_time":3.111328144},
{"learn":[0.7510650971],"iteration":153,"passed_time":0.5643559713,"remaining_time":3.100293193},
{"learn":[0.7500774183],"iteration":154,"passed_time":0.5664490523,"remaining_time":3.088060962},
{"learn":[0.7492583017],"iteration":155,"passed_time":0.568722798,"remaining_time":3.076936164},
{"learn":[0.7483380694],"iteration":156,"passed_time":0.5711841646,"remaining_time":3.066931534},
{"learn":[0.7479709915],"iteration":157,"passed_time":0.5730225886,"remaining_time":3.053702656},
{"learn":[0.7473169546],"iteration":158,"passed_time":0.5748691329,"remaining_time":3.040660005},
{"learn":[0.7464555968],"iteration":159,"passed_time":0.5767975605,"remaining_time":3.028187193},
{"learn":[0.7449780245],"iteration":160,"passed_time":0.5788841345,"remaining_time":3.016669496},
{"learn":[0.7444245134],"iteration":161,"passed_time":0.5810657143,"remaining_time":3.005759682},
{"learn":[0.7436374421],"iteration":162,"passed_time":0.5830220224,"remaining_time":2.993800201},
{"learn":[0.7429844001],"iteration":163,"passed_time":0.5849505327,"remaining_time":2.981821008},
{"learn":[0.7416958915],"iteration":164,"passed_time":0.5869150507,"remaining_time":2.970145863},
{"learn":[0.740792615],"iteration":165,"passed_time":0.588856818,"remaining_time":2.958473411},
{"learn":[0.7399340192],"iteration":166,"passed_time":0.5907702519,"remaining_time":2.946776167},
{"learn":[0.739305822],"iteration":167,"passed_time":0.5928479982,"remaining_time":2.936009134},
{"learn":[0.7385393116],"iteration":168,"passed_time":0.5947871914,"remaining_time":2.924663645},
{"learn":[0.7377920774],"iteration":169,"passed_time":0.5966466812,"remaining_time":2.913039679},
{"learn":[0.7372769494],"iteration":170,"passed_time":0.598591446,"remaining_time":2.901943326},
{"learn":[0.7368369184],"iteration":171,"passed_time":0.600412159,"remaining_time":2.890356208},
{"learn":[0.7354232862],"iteration":172,"passed_time":0.60254095,"remaining_time":2.880354715},
{"learn":[0.7341384909],"iteration":173,"passed_time":0.6046057379,"remaining_time":2.870139882},
{"learn":[0.7337591586],"iteration":174,"passed_time":0.6067933545,"remaining_time":2.860597243},
{"learn":[0.7330083031],"iteration":175,"passed_time":0.6091846337,"remaining_time":2.852091694},
{"learn":[0.7323623174],"iteration":176,"passed_time":0.6113388031,"remaining_time":2.84255274},
{"learn":[0.7311822252],"iteration":177,"passed_time":0.6132318045,"remaining_time":2.831890693},
{"learn":[0.7308192019],"iteration":178,"passed_time":0.6159549538,"remaining_time":2.825134173},
{"learn":[0.729180347],"iteration":179,"passed_time":0.6182348308,"remaining_time":2.816403118},
{"learn":[0.7288369472],"iteration":180,"passed_time":0.6202960898,"remaining_time":2.80675413},
{"learn":[0.7282041754],"iteration":181,"passed_time":0.6226837243,"remaining_time":2.79865542},
{"learn":[0.7269707324],"iteration":182,"passed_time":0.6245844173,"remaining_time":2.788445185},
{"learn":[0.7262220542],"iteration":183,"passed_time":0.6268507928,"remaining_time":2.779946994},
{"learn":[0.7255036346],"iteration":184,"passed_time":0.6287647828,"remaining_time":2.769963773},
{"learn":[0.7250075476],"iteration":185,"passed_time":0.630946628,"remaining_time":2.761239544},
{"learn":[0.7243577101],"iteration":186,"passed_time":0.6331157396,"remaining_time":2.752529927},
{"learn":[0.7228681346],"iteration":187,"passed_time":0.6352045129,"remaining_time":2.743542896},
{"learn":[0.7218092511],"iteration":188,"passed_time":0.637154339,"remaining_time":2.73403264},
{"learn":[0.7214770095],"iteration":189,"passed_time":0.6394888099,"remaining_time":2.726241768},
{"learn":[0.7207198583],"iteration":190,"passed_time":0.6417447774,"remaining_time":2.718175523},
{"learn":[0.7199272667],"iteration":191,"passed_time":0.6442597122,"remaining_time":2.711259622},
{"learn":[0.7187367319],"iteration":192,"passed_time":0.6463265905,"remaining_time":2.702515847},
{"learn":[0.7177673985],"iteration":193,"passed_time":0.6488142254,"remaining_time":2.695588998},
{"learn":[0.7165946021],"iteration":194,"passed_time":0.6509543422,"remaining_time":2.687273054},
{"learn":[0.7155488251],"iteration":195,"passed_time":0.652845866,"remaining_time":2.678000389},
{"learn":[0.7151042914],"iteration":196,"passed_time":0.6547557908,"remaining_time":2.668877665},
{"learn":[0.7145775529],"iteration":197,"passed_time":0.6568158594,"remaining_time":2.660435956},
{"learn":[0.7138633203],"iteration":198,"passed_time":0.6585590098,"remaining_time":2.650782748},
{"learn":[0.7134078378],"iteration":199,"passed_time":0.6603366085,"remaining_time":2.641346434},
{"learn":[0.7129205555],"iteration":200,"passed_time":0.6627474137,"remaining_time":2.634503401},
{"learn":[0.7116335482],"iteration":201,"passed_time":0.6647683365,"remaining_time":2.626164022},
{"learn":[0.7104437881],"iteration":202,"passed_time":0.6668103592,"remaining_time":2.617969736},
{"learn":[0.7097822656],"iteration":203,"passed_time":0.6688373694,"remaining_time":2.609777186},
{"learn":[0.7087582315],"iteration":204,"passed_time":0.6709465076,"remaining_time":2.601963286},
{"learn":[0.7081929176],"iteration":205,"passed_time":0.6729764653,"remaining_time":2.59389958},
{"learn":[0.7073829884],"iteration":206,"passed_time":0.6750502178,"remaining_time":2.586061945},
{"learn":[0.7064818336],"iteration":207,"passed_time":0.6770507855,"remaining_time":2.578001068},
{"learn":[0.7059706682],"iteration":208,"passed_time":0.6793052454,"remaining_time":2.570959087},
{"learn":[0.7051520008],"iteration":209,"passed_time":0.6812195591,"remaining_time":2.562683103},
{"learn":[0.7046744512],"iteration":210,"passed_time":0.6831590208,"remaining_time":2.554561457},
{"learn":[0.7036874848],"iteration":211,"passed_time":0.6856083465,"remaining_time":2.548393288},
{"learn":[0.7027069909],"iteration":212,"passed_time":0.687533318,"remaining_time":2.540322635},
{"learn":[0.7017862713],"iteration":213,"passed_time":0.6896650104,"remaining_time":2.533068683},
{"learn":[0.7012170815],"iteration":214,"passed_time":0.6917128847,"remaining_time":2.525556346},
{"learn":[0.7006267492],"iteration":215,"passed_time":0.6936475513,"remaining_time":2.517683705},
{"learn":[0.7001743934],"iteration":216,"passed_time":0.6956188407,"remaining_time":2.509997937},
{"learn":[0.6996794221],"iteration":217,"passed_time":0.6974630085,"remaining_time":2.50190859},
{"learn":[0.6990645486],"iteration":218,"passed_time":0.6994533531,"remaining_time":2.494397574},
{"learn":[0.6985605536],"iteration":219,"passed_time":0.7016199269,"remaining_time":2.487561559},
{"learn":[0.6981262763],"iteration":220,"passed_time":0.7037012456,"remaining_time":2.480467286},
{"learn":[0.6973027653],"iteration":221,"passed_time":0.7057891691,"remaining_time":2.473441322},
{"learn":[0.6968401865],"iteration":222,"passed_time":0.7079029683,"remaining_time":2.466549804},
{"learn":[0.6963672691],"iteration":223,"passed_time":0.7098319128,"remaining_time":2.459060555},
{"learn":[0.6953784927],"iteration":224,"passed_time":0.711772831,"remaining_time":2.451661973},
{"learn":[0.694354343],"iteration":225,"passed_time":0.7136981264,"remaining_time":2.444258185},
{"learn":[0.6937817654],"iteration":226,"passed_time":0.7155891929,"remaining_time":2.436786106},
{"learn":[0.6932385152],"iteration":227,"passed_time":0.71759197,"remaining_time":2.429741232},
{"learn":[0.6926669051],"iteration":228,"passed_time":0.7195871437,"remaining_time":2.422714794},
{"learn":[0.692371429],"iteration":229,"passed_time":0.7214691149,"remaining_time":2.415353124},
{"learn":[0.6920751276],"iteration":230,"passed_time":0.7235813123,"remaining_time":2.408805321},
{"learn":[0.6912973423],"iteration":231,"passed_time":0.7258406363,"remaining_time":2.402782796},
{"learn":[0.6909174327],"iteration":232,"passed_time":0.7276346848,"remaining_time":2.395260958},
{"learn":[0.689355367],"iteration":233,"passed_time":0.7296487315,"remaining_time":2.388508241},
{"learn":[0.6889398582],"iteration":234,"passed_time":0.7317931547,"remaining_time":2.38222027},
{"learn":[0.6886469146],"iteration":235,"passed_time":0.7336757879,"remaining_time":2.375119924},
{"learn":[0.6883384468],"iteration":236,"passed_time":0.7356750057,"remaining_time":2.368438942},
{"learn":[0.6879684299],"iteration":237,"passed_time":0.7374526173,"remaining_time":2.361087791},
{"learn":[0.6872544336],"iteration":238,"passed_time":0.739396083,"remaining_time":2.354311377},
{"learn":[0.6869369455],"iteration":239,"passed_time":0.7411482656,"remaining_time":2.346969508},
{"learn":[0.6864474509],"iteration":240,"passed_time":0.7433289498,"remaining_time":2.341023539},
{"learn":[0.6852098342],"iteration":241,"passed_time":0.745192047,"remaining_time":2.334113932},
{"learn":[0.6848751539],"iteration":242,"passed_time":0.747212838,"remaining_time":2.327737113},
{"learn":[0.6844255462],"iteration":243,"passed_time":0.7490333093,"remaining_time":2.320775335},
{"learn":[0.683364998],"iteration":244,"passed_time":0.7507271061,"remaining_time":2.313465164},
{"learn":[0.6826714201],"iteration":245,"passed_time":0.75250221,"remaining_time":2.306449863},
{"learn":[0.6822038903],"iteration":246,"passed_time":0.7544975568,"remaining_time":2.300148422},
{"learn":[0.6818960782],"iteration":247,"passed_time":0.7564853731,"remaining_time":2.293858873},
{"learn":[0.680487545],"iteration":248,"passed_time":0.7583473266,"remaining_time":2.287224266},
{"learn":[0.6801563958],"iteration":249,"passed_time":0.7601646611,"remaining_time":2.280493983},
{"learn":[0.6793400983],"iteration":250,"passed_time":0.7620136219,"remaining_time":2.273897222},
{"learn":[0.6791033394],"iteration":251,"passed_time":0.763885905,"remaining_time":2.267407369},
{"learn":[0.6786584136],"iteration":252,"passed_time":0.7659884737,"remaining_time":2.261633952},
{"learn":[0.6772292548],"iteration":253,"passed_time":0.7679953461,"remaining_time":2.255608379},
{"learn":[0.6765673111],"iteration":254,"passed_time":0.769714855,"remaining_time":2.248774773},
{"learn":[0.6763649041],"iteration":255,"passed_time":0.7726957559,"remaining_time":2.24564704},
{"learn":[0.6759460404],"iteration":256,"passed_time":0.7745054979,"remaining_time":2.239134572},
{"learn":[0.6750041849],"iteration":257,"passed_time":0.7766709796,"remaining_time":2.233681654},
{"learn":[0.6745311276],"iteration":258,"passed_time":0.7785179079,"remaining_time":2.22734274},
{"learn":[0.6730282166],"iteration":259,"passed_time":0.7805392194,"remaining_time":2.221534701},
{"learn":[0.6727210957],"iteration":260,"passed_time":0.7823782301,"remaining_time":2.21523951},
{"learn":[0.6714304425],"iteration":261,"passed_time":0.7842674664,"remaining_time":2.20911981},
{"learn":[0.6711964351],"iteration":262,"passed_time":0.7860790077,"remaining_time":2.202814558},
{"learn":[0.6704473114],"iteration":263,"passed_time":0.7881205182,"remaining_time":2.197184475},
{"learn":[0.6694011999],"iteration":264,"passed_time":0.7900410936,"remaining_time":2.191246052},
{"learn":[0.6679968318],"iteration":265,"passed_time":0.7917889359,"remaining_time":2.184861199},
{"learn":[0.6670230532],"iteration":266,"passed_time":0.7938125994,"remaining_time":2.179268297},
{"learn":[0.6667335691],"iteration":267,"passed_time":0.7957303804,"remaining_time":2.17341283},
{"learn":[0.6662773666],"iteration":268,"passed_time":0.7976038574,"remaining_time":2.167466244},
{"learn":[0.6650799357],"iteration":269,"passed_time":0.7994426254,"remaining_time":2.161455987},
{"learn":[0.6644079582],"iteration":270,"passed_time":0.8012661094,"remaining_time":2.155435401},
{"learn":[0.6639668863],"iteration":271,"passed_time":0.8030292835,"remaining_time":2.149284259},
{"learn":[0.6631906128],"iteration":272,"passed_time":0.8050223934,"remaining_time":2.143777582},
{"learn":[0.6630621258],"iteration":273,"passed_time":0.8070257719,"remaining_time":2.13832376},
{"learn":[0.6627844624],"iteration":274,"passed_time":0.8087728305,"remaining_time":2.132219281},
{"learn":[0.6612930388],"iteration":275,"passed_time":0.8107656734,"remaining_time":2.126791114},
{"learn":[0.6604587169],"iteration":276,"passed_time":0.812596807,"remaining_time":2.120965673},
{"learn":[0.6600234145],"iteration":277,"passed_time":0.8144234914,"remaining_time":2.115157413},
{"learn":[0.6593980869],"iteration":278,"passed_time":0.8164596177,"remaining_time":2.10991894},
{"learn":[0.6583754547],"iteration":279,"passed_time":0.8187292356,"remaining_time":2.105303749},
{"learn":[0.6572255153],"iteration":280,"passed_time":0.8206382374,"remaining_time":2.099782536},
{"learn":[0.6563104451],"iteration":281,"passed_time":0.822511411,"remaining_time":2.09419572},
{"learn":[0.6560821889],"iteration":282,"passed_time":0.8245276896,"remaining_time":2.088997715},
{"learn":[0.6556298245],"iteration":283,"passed_time":0.8264534805,"remaining_time":2.083593986},
{"learn":[0.6553819335],"iteration":284,"passed_time":0.8282733394,"remaining_time":2.077948904},
{"learn":[0.6544722306],"iteration":285,"passed_time":0.8305346716,"remaining_time":2.073432712},
{"learn":[0.6532258883],"iteration":286,"passed_time":0.8324655917,"remaining_time":2.068111383},
{"learn":[0.6530351452],"iteration":287,"passed_time":0.8344628339,"remaining_time":2.062977562},
{"learn":[0.6525242119],"iteration":288,"passed_time":0.8364282066,"remaining_time":2.057787041},
{"learn":[0.6518453641],"iteration":289,"passed_time":0.8383262279,"remaining_time":2.052453868},
{"learn":[0.651196627],"iteration":290,"passed_time":0.8402068991,"remaining_time":2.047102032},
{"learn":[0.650466436],"iteration":291,"passed_time":0.8421537425,"remaining_time":2.041934417},
{"learn":[0.6499145349],"iteration":292,"passed_time":0.8439534688,"remaining_time":2.036433797},
{"learn":[0.6488427482],"iteration":293,"passed_time":0.8458437769,"remaining_time":2.031175872},
{"learn":[0.6480343275],"iteration":294,"passed_time":0.847982467,"remaining_time":2.02653437},
{"learn":[0.6478230207],"iteration":295,"passed_time":0.8500350496,"remaining_time":2.021704983},
{"learn":[0.6473059075],"iteration":296,"passed_time":0.8519205594,"remaining_time":2.016498832},
{"learn":[0.647052666],"iteration":297,"passed_time":0.8538001995,"remaining_time":2.011301141},
{"learn":[0.6462602947],"iteration":298,"passed_time":0.8555733764,"remaining_time":2.005876043},
{"learn":[0.6458869325],"iteration":299,"passed_time":0.8574512824,"remaining_time":2.000719659},
{"learn":[0.645320676],"iteration":300,"passed_time":0.8596530302,"remaining_time":1.996337103},
{"learn":[0.6442310249],"iteration":301,"passed_time":0.8616777927,"remaining_time":1.991559931},
{"learn":[0.6440099812],"iteration":302,"passed_time":0.8635384327,"remaining_time":1.986423391},
{"learn":[0.6435780135],"iteration":303,"passed_time":0.8655465795,"remaining_time":1.981646116},
{"learn":[0.6425523168],"iteration":304,"passed_time":0.8674197126,"remaining_time":1.976579345},
{"learn":[0.6424545936],"iteration":305,"passed_time":0.869340361,"remaining_time":1.971641211},
{"learn":[0.6421741322],"iteration":306,"passed_time":0.8712601575,"remaining_time":1.966720812},
{"learn":[0.6412789669],"iteration":307,"passed_time":0.873056835,"remaining_time":1.961543279},
{"learn":[0.6407324359],"iteration":308,"passed_time":0.8752469094,"remaining_time":1.95726736},
{"learn":[0.6400269927],"iteration":309,"passed_time":0.8775322977,"remaining_time":1.95321705},
{"learn":[0.6397653779],"iteration":310,"passed_time":0.8793972149,"remaining_time":1.948246563},
{"learn":[0.6392639411],"iteration":311,"passed_time":0.8814555209,"remaining_time":1.943722431},
{"learn":[0.6391427352],"iteration":312,"passed_time":0.8833022874,"remaining_time":1.938749749},
{"learn":[0.6379213685],"iteration":313,"passed_time":0.8852231333,"remaining_time":1.93395882},
{"learn":[0.6366011244],"iteration":314,"passed_time":0.8873095698,"remaining_time":1.929546207},
{"learn":[0.6362153433],"iteration":315,"passed_time":0.8890432303,"remaining_time":1.924384714},
{"learn":[0.6361086198],"iteration":316,"passed_time":0.8908834343,"remaining_time":1.919474403},
{"learn":[0.6350212443],"iteration":317,"passed_time":0.8926326265,"remaining_time":1.914388212},
{"learn":[0.6338159793],"iteration":318,"passed_time":0.894658908,"remaining_time":1.909914471},
{"learn":[0.6329522544],"iteration":319,"passed_time":0.8965517289,"remaining_time":1.905172424},
{"learn":[0.632790949],"iteration":320,"passed_time":0.8987198874,"remaining_time":1.901030541},
{"learn":[0.6318377696],"iteration":321,"passed_time":0.9006235827,"remaining_time":1.896344065},
{"learn":[0.6316874837],"iteration":322,"passed_time":0.902571382,"remaining_time":1.891767262},
{"learn":[0.631327545],"iteration":323,"passed_time":0.9044968951,"remaining_time":1.887160189},
{"learn":[0.6304952336],"iteration":324,"passed_time":0.9062968024,"remaining_time":1.882308744},
{"learn":[0.6303770169],"iteration":325,"passed_time":0.9080676593,"remaining_time":1.877415958},
{"learn":[0.6302855014],"iteration":326,"passed_time":0.9103110601,"remaining_time":1.873514812},
{"learn":[0.6297170286],"iteration":327,"passed_time":0.9120766592,"remaining_time":1.868644863},
{"learn":[0.6291063475],"iteration":328,"passed_time":0.9140148317,"remaining_time":1.864145751},
{"learn":[0.6288312448],"iteration":329,"passed_time":0.9159193526,"remaining_time":1.859593837},
{"learn":[0.6285329376],"iteration":330,"passed_time":0.9177817571,"remaining_time":1.854972796},
{"learn":[0.6283009135],"iteration":331,"passed_time":0.9196268552,"remaining_time":1.850333552},
{"learn":[0.6280803888],"iteration":332,"passed_time":0.921580023,"remaining_time":1.845927553},
{"learn":[0.6275131028],"iteration":333,"passed_time":0.9235359671,"remaining_time":1.841541779},
{"learn":[0.6273906081],"iteration":334,"passed_time":0.9253087038,"remaining_time":1.83680683},
{"learn":[0.6266542888],"iteration":335,"passed_time":0.9274352853,"remaining_time":1.832788778},
{"learn":[0.6257924827],"iteration":336,"passed_time":0.9293364175,"remaining_time":1.828338412},
{"learn":[0.6256797996],"iteration":337,"passed_time":0.9314022094,"remaining_time":1.824225629},
{"learn":[0.6250055266],"iteration":338,"passed_time":0.9336176237,"remaining_time":1.820416665},
{"learn":[0.6245341063],"iteration":339,"passed_time":0.9358032533,"remaining_time":1.816559256},
{"learn":[0.623296764],"iteration":340,"passed_time":0.9380022963,"remaining_time":1.812737575},
{"learn":[0.6223241444],"iteration":341,"passed_time":0.9402048986,"remaining_time":1.808932232},
{"learn":[0.6221947405],"iteration":342,"passed_time":0.9421400369,"remaining_time":1.804623919},
{"learn":[0.6212174976],"iteration":343,"passed_time":0.9452331944,"remaining_time":1.80253772},
{"learn":[0.6205259748],"iteration":344,"passed_time":0.9472294746,"remaining_time":1.798363205},
{"learn":[0.6196340409],"iteration":345,"passed_time":0.949309067,"remaining_time":1.794358757},
{"learn":[0.6187740752],"iteration":346,"passed_time":0.9514729763,"remaining_time":1.790524074},
{"learn":[0.6178849738],"iteration":347,"passed_time":0.9535910737,"remaining_time":1.786613161},
{"learn":[0.617731155],"iteration":348,"passed_time":0.9560061862,"remaining_time":1.783266554},
{"learn":[0.6175221358],"iteration":349,"passed_time":0.9580820965,"remaining_time":1.779295322},
{"learn":[0.6173184358],"iteration":350,"passed_time":0.9600562714,"remaining_time":1.775146781},
{"learn":[0.6164668794],"iteration":351,"passed_time":0.9621359013,"remaining_time":1.771204727},
{"learn":[0.61627046],"iteration":352,"passed_time":0.9642008609,"remaining_time":1.767246337},
{"learn":[0.6159772044],"iteration":353,"passed_time":0.9660796213,"remaining_time":1.762958857},
{"learn":[0.6150561964],"iteration":354,"passed_time":0.9681485352,"remaining_time":1.759030437},
{"learn":[0.6147307445],"iteration":355,"passed_time":0.9702233801,"remaining_time":1.755123193},
{"learn":[0.6140815598],"iteration":356,"passed_time":0.9726423354,"remaining_time":1.751845999},
{"learn":[0.6135903646],"iteration":357,"passed_time":0.9746524025,"remaining_time":1.747840342},
{"learn":[0.6130890849],"iteration":358,"passed_time":0.9770019568,"remaining_time":1.744451962},
{"learn":[0.6119842511],"iteration":359,"passed_time":0.9794743564,"remaining_time":1.741287745},
{"learn":[0.6111532767],"iteration":360,"passed_time":0.9816065038,"remaining_time":1.737525086},
{"learn":[0.6102820816],"iteration":361,"passed_time":0.983801283,"remaining_time":1.733881819},
{"learn":[0.6095708559],"iteration":362,"passed_time":0.9858275957,"remaining_time":1.729950905},
{"learn":[0.6086385028],"iteration":363,"passed_time":0.9880711914,"remaining_time":1.726410104},
{"learn":[0.6085440615],"iteration":364,"passed_time":0.9901002947,"remaining_time":1.722503252},
{"learn":[0.6075538272],"iteration":365,"passed_time":0.9924533063,"remaining_time":1.719167749},
{"learn":[0.6075020278],"iteration":366,"passed_time":0.9945820991,"remaining_time":1.715450868},
{"learn":[0.6070065165],"iteration":367,"passed_time":0.9966879263,"remaining_time":1.711703178},
{"learn":[0.6063961636],"iteration":368,"passed_time":0.9985666766,"remaining_time":1.707576078},
{"learn":[0.6053872486],"iteration":369,"passed_time":1.001246702,"remaining_time":1.704825466},
{"learn":[0.6048459169],"iteration":370,"passed_time":1.003291403,"remaining_time":1.700998093},
{"learn":[0.604648771],"iteration":371,"passed_time":1.005602745,"remaining_time":1.697630441},
{"learn":[0.6041366688],"iteration":372,"passed_time":1.00765604,"remaining_time":1.693834684},
{"learn":[0.6032752523],"iteration":373,"passed_time":1.009892351,"remaining_time":1.690354577},
{"learn":[0.6032031789],"iteration":374,"passed_time":1.011809698,"remaining_time":1.686349497},
{"learn":[0.6027453499],"iteration":375,"passed_time":1.014380679,"remaining_time":1.683440276},
{"learn":[0.6024076595],"iteration":376,"passed_time":1.016706842,"remaining_time":1.680128283},
{"learn":[0.6019738021],"iteration":377,"passed_time":1.018726147,"remaining_time":1.67631657},
{"learn":[0.601205778],"iteration":378,"passed_time":1.020850453,"remaining_time":1.672686363},
{"learn":[0.6002632362],"iteration":379,"passed_time":1.022919485,"remaining_time":1.668973897},
{"learn":[0.5996552854],"iteration":380,"passed_time":1.025056083,"remaining_time":1.66537983},
{"learn":[0.5993622657],"iteration":381,"passed_time":1.027182058,"remaining_time":1.661776208},
{"learn":[0.5988850861],"iteration":382,"passed_time":1.029143412,"remaining_time":1.657915105},
{"learn":[0.5981144631],"iteration":383,"passed_time":1.030991887,"remaining_time":1.653882819},
{"learn":[0.5977953001],"iteration":384,"passed_time":1.032702679,"remaining_time":1.649641943},
{"learn":[0.5976637078],"iteration":385,"passed_time":1.034999352,"remaining_time":1.64634612},
{"learn":[0.5974859856],"iteration":386,"passed_time":1.037095557,"remaining_time":1.642737924},
{"learn":[0.5963374251],"iteration":387,"passed_time":1.039057235,"remaining_time":1.638925329},
{"learn":[0.5954185059],"iteration":388,"passed_time":1.040941704,"remaining_time":1.635000979},
{"learn":[0.5952089052],"iteration":389,"passed_time":1.042945386,"remaining_time":1.631273552},
{"learn":[0.5947219734],"iteration":390,"passed_time":1.044963274,"remaining_time":1.627577069},
{"learn":[0.5938404415],"iteration":391,"passed_time":1.046974528,"remaining_time":1.62387886},
{"learn":[0.5937528435],"iteration":392,"passed_time":1.048830931,"remaining_time":1.619950064},
{"learn":[0.5932517874],"iteration":393,"passed_time":1.050724172,"remaining_time":1.616088447},
{"learn":[0.5926432207],"iteration":394,"passed_time":1.052722555,"remaining_time":1.612397838},
{"learn":[0.5919593058],"iteration":395,"passed_time":1.054700522,"remaining_time":1.608684634},
{"learn":[0.5914133697],"iteration":396,"passed_time":1.056685921,"remaining_time":1.604991462},
{"learn":[0.5907876546],"iteration":397,"passed_time":1.058817308,"remaining_time":1.601527687},
{"learn":[0.5906607177],"iteration":398,"passed_time":1.060816763,"remaining_time":1.597871866},
{"learn":[0.5905310224],"iteration":399,"passed_time":1.062945102,"remaining_time":1.594417653},
{"learn":[0.5900885961],"iteration":400,"passed_time":1.065285655,"remaining_time":1.591287051},
{"learn":[0.5898141623],"iteration":401,"passed_time":1.067319122,"remaining_time":1.587703569},
{"learn":[0.5889914584],"iteration":402,"passed_time":1.069453985,"remaining_time":1.584277988},
{"learn":[0.5888064476],"iteration":403,"passed_time":1.071415809,"remaining_time":1.58060352},
{"learn":[0.5882800732],"iteration":404,"passed_time":1.073389095,"remaining_time":1.576954349},
{"learn":[0.5875499382],"iteration":405,"passed_time":1.075278537,"remaining_time":1.573190766},
{"learn":[0.587278187],"iteration":406,"passed_time":1.077353846,"remaining_time":1.569707201},
{"learn":[0.5867481897],"iteration":407,"passed_time":1.079415682,"remaining_time":1.566210989},
{"learn":[0.5861233692],"iteration":408,"passed_time":1.081774598,"remaining_time":1.56315107},
{"learn":[0.5856821474],"iteration":409,"passed_time":1.08374304,"remaining_time":1.559532668},
{"learn":[0.5854574643],"iteration":410,"passed_time":1.085754974,"remaining_time":1.555984622},
{"learn":[0.5842299565],"iteration":411,"passed_time":1.087879497,"remaining_time":1.552604719},
{"learn":[0.5834891759],"iteration":412,"passed_time":1.089788219,"remaining_time":1.548924176},
{"learn":[0.5827798118],"iteration":413,"passed_time":1.09223884,"remaining_time":1.546019228},
{"learn":[0.5817361157],"iteration":414,"passed_time":1.094366888,"remaining_time":1.542661758},
{"learn":[0.5806089582],"iteration":415,"passed_time":1.096265994,"remaining_time":1.538988799},
{"learn":[0.5803838603],"iteration":416,"passed_time":1.098171618,"remaining_time":1.535333461},
{"learn":[0.5797474917],"iteration":417,"passed_time":1.100072745,"remaining_time":1.531680234},
{"learn":[0.5794601938],"iteration":418,"passed_time":1.101948078,"remaining_time":1.527999602},
{"learn":[0.5788437484],"iteration":419,"passed_time":1.103870491,"remaining_time":1.524392583},
{"learn":[0.5784105691],"iteration":420,"passed_time":1.105947044,"remaining_time":1.521005555},
{"learn":[0.5772664052],"iteration":421,"passed_time":1.107836837,"remaining_time":1.517368938},
{"learn":[0.5761573899],"iteration":422,"passed_time":1.110029034,"remaining_time":1.51415308},
{"learn":[0.5756092755],"iteration":423,"passed_time":1.112011785,"remaining_time":1.510657519},
{"learn":[0.5747082267],"iteration":424,"passed_time":1.114108304,"remaining_time":1.507322999},
{"learn":[0.573905035],"iteration":425,"passed_time":1.116338113,"remaining_time":1.504173889},
{"learn":[0.5738172115],"iteration":426,"passed_time":1.118216408,"remaining_time":1.500557381},
{"learn":[0.5731974953],"iteration":427,"passed_time":1.120229663,"remaining_time":1.497129363},
{"learn":[0.572325658],"iteration":428,"passed_time":1.122439156,"remaining_time":1.493969133},
{"learn":[0.5714753773],"iteration":429,"passed_time":1.124369249,"remaining_time":1.490442958},
{"learn":[0.5704920937],"iteration":430,"passed_time":1.126345572,"remaining_time":1.486985222},
{"learn":[0.570254296],"iteration":431,"passed_time":1.128332519,"remaining_time":1.483548312},
{"learn":[0.5701697554],"iteration":432,"passed_time":1.130412788,"remaining_time":1.480240302},
{"learn":[0.5695554838],"iteration":433,"passed_time":1.132487006,"remaining_time":1.476930058},
{"learn":[0.5685423421],"iteration":434,"passed_time":1.134534967,"remaining_time":1.473591395},
{"learn":[0.5670928404],"iteration":435,"passed_time":1.136666554,"remaining_time":1.470366827},
{"learn":[0.5661036966],"iteration":436,"passed_time":1.138620576,"remaining_time":1.4669185},
{"learn":[0.5652713404],"iteration":437,"passed_time":1.140518792,"remaining_time":1.46340539},
{"learn":[0.5643045541],"iteration":438,"passed_time":1.142639907,"remaining_time":1.460184483},
{"learn":[0.5630812058],"iteration":439,"passed_time":1.144594857,"remaining_time":1.456757091},
{"learn":[0.5622844703],"iteration":440,"passed_time":1.146384907,"remaining_time":1.453127354},
{"learn":[0.5621569628],"iteration":441,"passed_time":1.148298214,"remaining_time":1.449661547},
{"learn":[0.5612403028],"iteration":442,"passed_time":1.15019497,"remaining_time":1.446181938},
{"learn":[0.561119609],"iteration":443,"passed_time":1.152035706,"remaining_time":1.442639307},
{"learn":[0.5601572256],"iteration":444,"passed_time":1.15394975,"remaining_time":1.439195756},
{"learn":[0.5592995888],"iteration":445,"passed_time":1.156173369,"remaining_time":1.436143601},
{"learn":[0.5582301845],"iteration":446,"passed_time":1.158479986,"remaining_time":1.433197835},
{"learn":[0.5580116005],"iteration":447,"passed_time":1.160481176,"remaining_time":1.429878592},
{"learn":[0.5573418685],"iteration":448,"passed_time":1.162444578,"remaining_time":1.426518848},
{"learn":[0.5572427061],"iteration":449,"passed_time":1.164297634,"remaining_time":1.423030442},
{"learn":[0.5568321593],"iteration":450,"passed_time":1.166380468,"remaining_time":1.419828995},
{"learn":[0.5561785451],"iteration":451,"passed_time":1.16839178,"remaining_time":1.416545787},
{"learn":[0.5561201779],"iteration":452,"passed_time":1.170280566,"remaining_time":1.413120242},
{"learn":[0.5551083168],"iteration":453,"passed_time":1.172050108,"remaining_time":1.40955806},
{"learn":[0.5550248646],"iteration":454,"passed_time":1.173943096,"remaining_time":1.406151621},
{"learn":[0.5542400886],"iteration":455,"passed_time":1.175844537,"remaining_time":1.402761903},
{"learn":[0.5537387715],"iteration":456,"passed_time":1.177647251,"remaining_time":1.399261394},
{"learn":[0.5531037585],"iteration":457,"passed_time":1.17943822,"remaining_time":1.3957544},
{"learn":[0.5530485484],"iteration":458,"passed_time":1.181550443,"remaining_time":1.392633529},
{"learn":[0.5524125287],"iteration":459,"passed_time":1.183346817,"remaining_time":1.389146263},
{"learn":[0.5518012386],"iteration":460,"passed_time":1.18509069,"remaining_time":1.38560495},
{"learn":[0.5512568695],"iteration":461,"passed_time":1.186845575,"remaining_time":1.382084241},
{"learn":[0.550972959],"iteration":462,"passed_time":1.188894002,"remaining_time":1.378911618},
{"learn":[0.5502120088],"iteration":463,"passed_time":1.190743324,"remaining_time":1.375513839},
{"learn":[0.5497859092],"iteration":464,"passed_time":1.192612438,"remaining_time":1.372145493},
{"learn":[0.5496356056],"iteration":465,"passed_time":1.194505061,"remaining_time":1.368810521},
{"learn":[0.5494779881],"iteration":466,"passed_time":1.196247004,"remaining_time":1.365309749},
{"learn":[0.5487339612],"iteration":467,"passed_time":1.198050198,"remaining_time":1.361886123},
{"learn":[0.5482595309],"iteration":468,"passed_time":1.19996641,"remaining_time":1.358597364},
{"learn":[0.5481059393],"iteration":469,"passed_time":1.201810381,"remaining_time":1.355232982},
{"learn":[0.5473625602],"iteration":470,"passed_time":1.203740954,"remaining_time":1.351972324},
{"learn":[0.5467552408],"iteration":471,"passed_time":1.205767579,"remaining_time":1.348824749},
{"learn":[0.5457911442],"iteration":472,"passed_time":1.207652432,"remaining_time":1.345523957},
{"learn":[0.5457141018],"iteration":473,"passed_time":1.209681717,"remaining_time":1.342389416},
{"learn":[0.5455278467],"iteration":474,"passed_time":1.211411174,"remaining_time":1.33892814},
{"learn":[0.544796207],"iteration":475,"passed_time":1.213179144,"remaining_time":1.335516537},
{"learn":[0.5438716839],"iteration":476,"passed_time":1.215429661,"remaining_time":1.332640907},
{"learn":[0.5433381288],"iteration":477,"passed_time":1.217362843,"remaining_time":1.329421347},
{"learn":[0.5431589629],"iteration":478,"passed_time":1.219173459,"remaining_time":1.326073846},
{"learn":[0.5429265795],"iteration":479,"passed_time":1.221107531,"remaining_time":1.322866492},
{"learn":[0.5426268492],"iteration":480,"passed_time":1.223077749,"remaining_time":1.319703434},
{"learn":[0.5420839171],"iteration":481,"passed_time":1.224911178,"remaining_time":1.31639832},
{"learn":[0.5419929505],"iteration":482,"passed_time":1.227070824,"remaining_time":1.31344848},
{"learn":[0.5414437148],"iteration":483,"passed_time":1.228995472,"remaining_time":1.310251371},
{"learn":[0.5412704341],"iteration":484,"passed_time":1.230767441,"remaining_time":1.306897386},
{"learn":[0.5407376134],"iteration":485,"passed_time":1.232725215,"remaining_time":1.303746421},
{"learn":[0.5405388057],"iteration":486,"passed_time":1.234627243,"remaining_time":1.300541634},
{"learn":[0.5404395887],"iteration":487,"passed_time":1.236519149,"remaining_time":1.297331566},
{"learn":[0.5399723695],"iteration":488,"passed_time":1.238330008,"remaining_time":1.294042197},
{"learn":[0.5388835778],"iteration":489,"passed_time":1.24030567,"remaining_time":1.290930391},
{"learn":[0.5386532537],"iteration":490,"passed_time":1.242068195,"remaining_time":1.287602263},
{"learn":[0.5379864618],"iteration":491,"passed_time":1.243970577,"remaining_time":1.284424904},
{"learn":[0.5378112385],"iteration":492,"passed_time":1.245856264,"remaining_time":1.281235549},
{"learn":[0.5370850887],"iteration":493,"passed_time":1.247846133,"remaining_time":1.278158185},
{"learn":[0.5368008396],"iteration":494,"passed_time":1.249870704,"remaining_time":1.275120617},
{"learn":[0.5358785941],"iteration":495,"passed_time":1.251646738,"remaining_time":1.271834588},
{"learn":[0.5358171212],"iteration":496,"passed_time":1.253525043,"remaining_time":1.268658142},
{"learn":[0.5349260627],"iteration":497,"passed_time":1.255314071,"remaining_time":1.265396915},
{"learn":[0.5347879267],"iteration":498,"passed_time":1.257279879,"remaining_time":1.262319077},
{"learn":[0.5338945617],"iteration":499,"passed_time":1.2589771,"remaining_time":1.2589771},
{"learn":[0.5330547475],"iteration":500,"passed_time":1.261052683,"remaining_time":1.25601854},
{"learn":[0.5326307706],"iteration":501,"passed_time":1.262761433,"remaining_time":1.252699589},
{"learn":[0.53254603],"iteration":502,"passed_time":1.264748158,"remaining_time":1.249661699},
{"learn":[0.5316757103],"iteration":503,"passed_time":1.266753726,"remaining_time":1.246646524},
{"learn":[0.5315872639],"iteration":504,"passed_time":1.268707048,"remaining_time":1.243584136},
{"learn":[0.5308715575],"iteration":505,"passed_time":1.270585571,"remaining_time":1.240453107},
{"learn":[0.5303798257],"iteration":506,"passed_time":1.272457566,"remaining_time":1.237320671},
{"learn":[0.5296802936],"iteration":507,"passed_time":1.274292674,"remaining_time":1.234157471},
{"learn":[0.5290210069],"iteration":508,"passed_time":1.276013204,"remaining_time":1.230888965},
{"learn":[0.5288811113],"iteration":509,"passed_time":1.277791538,"remaining_time":1.227682066},
{"learn":[0.5281837714],"iteration":510,"passed_time":1.279549923,"remaining_time":1.224461668},
{"learn":[0.5269875021],"iteration":511,"passed_time":1.281249804,"remaining_time":1.22119122},
{"learn":[0.5263319385],"iteration":512,"passed_time":1.283052691,"remaining_time":1.218024679},
{"learn":[0.5259187303],"iteration":513,"passed_time":1.284859657,"remaining_time":1.214867302},
{"learn":[0.5252071423],"iteration":514,"passed_time":1.286659414,"remaining_time":1.21170838},
{"learn":[0.5248176146],"iteration":515,"passed_time":1.288490942,"remaining_time":1.208584527},
{"learn":[0.5246204077],"iteration":516,"passed_time":1.290315351,"remaining_time":1.205459022},
{"learn":[0.5240605547],"iteration":517,"passed_time":1.292171314,"remaining_time":1.202367902},
{"learn":[0.5236363382],"iteration":518,"passed_time":1.293880008,"remaining_time":1.199145056},
{"learn":[0.5231699665],"iteration":519,"passed_time":1.295647036,"remaining_time":1.195981879},
{"learn":[0.5226260307],"iteration":520,"passed_time":1.2976396,"remaining_time":1.193031417},
{"learn":[0.5220659375],"iteration":521,"passed_time":1.299472195,"remaining_time":1.18993814},
{"learn":[0.5216349583],"iteration":522,"passed_time":1.3013046,"remaining_time":1.186849511},
{"learn":[0.5215430476],"iteration":523,"passed_time":1.303036551,"remaining_time":1.183674424},
{"learn":[0.5207809382],"iteration":524,"passed_time":1.305036947,"remaining_time":1.180747714},
{"learn":[0.5203862761],"iteration":525,"passed_time":1.306848342,"remaining_time":1.177654209},
{"learn":[0.5200621159],"iteration":526,"passed_time":1.308634139,"remaining_time":1.174542596},
{"learn":[0.5199164582],"iteration":527,"passed_time":1.310483271,"remaining_time":1.171492621},
{"learn":[0.5186455015],"iteration":528,"passed_time":1.31234835,"remaining_time":1.168461385},
{"learn":[0.5174951159],"iteration":529,"passed_time":1.314503002,"remaining_time":1.165691341},
{"learn":[0.5166755644],"iteration":530,"passed_time":1.316286029,"remaining_time":1.162595381},
{"learn":[0.5163213997],"iteration":531,"passed_time":1.318083141,"remaining_time":1.159516748},
{"learn":[0.5160739992],"iteration":532,"passed_time":1.319884244,"remaining_time":1.156446421},
{"learn":[0.5156203304],"iteration":533,"passed_time":1.321832483,"remaining_time":1.153509245},
{"learn":[0.5145400791],"iteration":534,"passed_time":1.32378503,"remaining_time":1.150579512},
{"learn":[0.5138287621],"iteration":535,"passed_time":1.325616244,"remaining_time":1.14754839},
{"learn":[0.5129437155],"iteration":536,"passed_time":1.327549244,"remaining_time":1.144609497},
{"learn":[0.5123208348],"iteration":537,"passed_time":1.329628017,"remaining_time":1.141799524},
{"learn":[0.5120288034],"iteration":538,"passed_time":1.331395228,"remaining_time":1.138725789},
{"learn":[0.5119581402],"iteration":539,"passed_time":1.333091359,"remaining_time":1.135596343},
{"learn":[0.5108410391],"iteration":540,"passed_time":1.335010111,"remaining_time":1.132661074},
{"learn":[0.5101723586],"iteration":541,"passed_time":1.336875897,"remaining_time":1.129684799},
{"learn":[0.5096581805],"iteration":542,"passed_time":1.338772584,"remaining_time":1.12673862},
{"learn":[0.5090891276],"iteration":543,"passed_time":1.340535776,"remaining_time":1.1236844},
{"learn":[0.5088581769],"iteration":544,"passed_time":1.342614128,"remaining_time":1.120898034},
{"learn":[0.5084442583],"iteration":545,"passed_time":1.345350824,"remaining_time":1.118661675},
{"learn":[0.5079175342],"iteration":546,"passed_time":1.347359734,"remaining_time":1.115820767},
{"learn":[0.5076343631],"iteration":547,"passed_time":1.349339537,"remaining_time":1.112958888},
{"learn":[0.5073599424],"iteration":548,"passed_time":1.351701138,"remaining_time":1.110413867},
{"learn":[0.5070119013],"iteration":549,"passed_time":1.354169173,"remaining_time":1.107956596},
{"learn":[0.5066546577],"iteration":550,"passed_time":1.356136116,"remaining_time":1.105090954},
{"learn":[0.5059815663],"iteration":551,"passed_time":1.358358454,"remaining_time":1.102435847},
{"learn":[0.5053197058],"iteration":552,"passed_time":1.36061926,"remaining_time":1.099813398},
{"learn":[0.5042980726],"iteration":553,"passed_time":1.363304432,"remaining_time":1.097533893},
{"learn":[0.5039707499],"iteration":554,"passed_time":1.365527349,"remaining_time":1.094882289},
{"learn":[0.5034667585],"iteration":555,"passed_time":1.368669794,"remaining_time":1.092966526},
{"learn":[0.5032644977],"iteration":556,"passed_time":1.370928639,"remaining_time":1.090343603},
{"learn":[0.502333653],"iteration":557,"passed_time":1.372708242,"remaining_time":1.087342371},
{"learn":[0.5018671662],"iteration":558,"passed_time":1.374772707,"remaining_time":1.084570239},
{"learn":[0.500865179],"iteration":559,"passed_time":1.376728807,"remaining_time":1.081715491},
{"learn":[0.5004525169],"iteration":560,"passed_time":1.378687886,"remaining_time":1.078866278},
{"learn":[0.4999863968],"iteration":561,"passed_time":1.380569493,"remaining_time":1.075959854},
{"learn":[0.4998090657],"iteration":562,"passed_time":1.382623565,"remaining_time":1.073190938},
{"learn":[0.4991752763],"iteration":563,"passed_time":1.384650237,"remaining_time":1.070403374},
{"learn":[0.4986787115],"iteration":564,"passed_time":1.386319743,"remaining_time":1.067343519},
{"learn":[0.4981925324],"iteration":565,"passed_time":1.388248111,"remaining_time":1.064487068},
{"learn":[0.4977715368],"iteration":566,"passed_time":1.390147569,"remaining_time":1.061611812},
{"learn":[0.4970394528],"iteration":567,"passed_time":1.392133186,"remaining_time":1.058805522},
{"learn":[0.4968817765],"iteration":568,"passed_time":1.393738506,"remaining_time":1.055714053},
{"learn":[0.4965001836],"iteration":569,"passed_time":1.395591636,"remaining_time":1.052814743},
{"learn":[0.4956667642],"iteration":570,"passed_time":1.397326782,"remaining_time":1.049830454},
{"learn":[0.495280326],"iteration":571,"passed_time":1.399311995,"remaining_time":1.047037647},
{"learn":[0.4948911226],"iteration":572,"passed_time":1.401249652,"remaining_time":1.044212219},
{"learn":[0.4947167736],"iteration":573,"passed_time":1.403178321,"remaining_time":1.041383214},
{"learn":[0.4946021199],"iteration":574,"passed_time":1.40536516,"remaining_time":1.038748161},
{"learn":[0.4943279791],"iteration":575,"passed_time":1.407332146,"remaining_time":1.03595283},
{"learn":[0.4942055379],"iteration":576,"passed_time":1.40918816,"remaining_time":1.033079015},
{"learn":[0.494026926],"iteration":577,"passed_time":1.411082189,"remaining_time":1.030236477},
{"learn":[0.4937787961],"iteration":578,"passed_time":1.412818225,"remaining_time":1.027282336},
{"learn":[0.4933079911],"iteration":579,"passed_time":1.414537471,"remaining_time":1.024320238},
{"learn":[0.492676248],"iteration":580,"passed_time":1.416418447,"remaining_time":1.021479052},
{"learn":[0.4920578369],"iteration":581,"passed_time":1.418318838,"remaining_time":1.018655111},
{"learn":[0.4913082027],"iteration":582,"passed_time":1.420512401,"remaining_time":1.016044033},
{"learn":[0.4902291978],"iteration":583,"passed_time":1.422399575,"remaining_time":1.013216136},
{"learn":[0.4896723885],"iteration":584,"passed_time":1.42441615,"remaining_time":1.010483252},
{"learn":[0.489113889],"iteration":585,"passed_time":1.426399315,"remaining_time":1.007729209},
{"learn":[0.4890543704],"iteration":586,"passed_time":1.4282626,"remaining_time":1.004893447},
{"learn":[0.4888811655],"iteration":587,"passed_time":1.430162177,"remaining_time":1.002086424},
{"learn":[0.488743507],"iteration":588,"passed_time":1.432302804,"remaining_time":0.9994506835},
{"learn":[0.4882716978],"iteration":589,"passed_time":1.43417974,"remaining_time":0.9966333787},
{"learn":[0.4876552366],"iteration":590,"passed_time":1.436004362,"remaining_time":0.9937830523},
{"learn":[0.487056904],"iteration":591,"passed_time":1.437980827,"remaining_time":0.9910408406},
{"learn":[0.486278025],"iteration":592,"passed_time":1.440009405,"remaining_time":0.9883369778},
{"learn":[0.4859650189],"iteration":593,"passed_time":1.442542412,"remaining_time":0.985980167},
{"learn":[0.4848475315],"iteration":594,"passed_time":1.444618343,"remaining_time":0.9833116452},
{"learn":[0.4842105402],"iteration":595,"passed_time":1.446743792,"remaining_time":0.9806786776},
{"learn":[0.4837289291],"iteration":596,"passed_time":1.448689158,"remaining_time":0.9779258473},
{"learn":[0.4837009265],"iteration":597,"passed_time":1.45064674,"remaining_time":0.9751839289},
{"learn":[0.4832503723],"iteration":598,"passed_time":1.452622491,"remaining_time":0.9724567928},
{"learn":[0.482678334],"iteration":599,"passed_time":1.454592769,"remaining_time":0.9697285129},
{"learn":[0.4821029881],"iteration":600,"passed_time":1.45648186,"remaining_time":0.9669488558},
{"learn":[0.4815268609],"iteration":601,"passed_time":1.458467945,"remaining_time":0.9642362823},
{"learn":[0.4810228008],"iteration":602,"passed_time":1.46060392,"remaining_time":0.961624803},
{"learn":[0.4809055761],"iteration":603,"passed_time":1.462450161,"remaining_time":0.9588249397},
{"learn":[0.4803678602],"iteration":604,"passed_time":1.46443829,"remaining_time":0.9561208673},
{"learn":[0.4799066822],"iteration":605,"passed_time":1.466460259,"remaining_time":0.9534411586},
{"learn":[0.47939041],"iteration":606,"passed_time":1.468683858,"remaining_time":0.9508941616},
{"learn":[0.4793432572],"iteration":607,"passed_time":1.47044796,"remaining_time":0.9480519742},
{"learn":[0.4790396983],"iteration":608,"passed_time":1.472543834,"remaining_time":0.9454263369},
{"learn":[0.4785691186],"iteration":609,"passed_time":1.474533986,"remaining_time":0.9427348438},
{"learn":[0.4779056989],"iteration":610,"passed_time":1.476479936,"remaining_time":0.940017504},
{"learn":[0.4774101811],"iteration":611,"passed_time":1.478461781,"remaining_time":0.9373254432},
{"learn":[0.4766212982],"iteration":612,"passed_time":1.480380044,"remaining_time":0.9345955578},
{"learn":[0.4762475931],"iteration":613,"passed_time":1.482239903,"remaining_time":0.9318316002},
{"learn":[0.4757422602],"iteration":614,"passed_time":1.484100543,"remaining_time":0.9290710716},
{"learn":[0.4753412395],"iteration":615,"passed_time":1.486208731,"remaining_time":0.9264677803},
{"learn":[0.4747315117],"iteration":616,"passed_time":1.488090262,"remaining_time":0.9237253976},
{"learn":[0.4743090166],"iteration":617,"passed_time":1.489963455,"remaining_time":0.9209806471},
{"learn":[0.4737463257],"iteration":618,"passed_time":1.491736385,"remaining_time":0.9181769995},
{"learn":[0.4730920361],"iteration":619,"passed_time":1.493743561,"remaining_time":0.9155202473},
{"learn":[0.4725858857],"iteration":620,"passed_time":1.49576371,"remaining_time":0.9128735042},
{"learn":[0.4722761334],"iteration":621,"passed_time":1.497607837,"remaining_time":0.9101218047},
{"learn":[0.4717077318],"iteration":622,"passed_time":1.499755236,"remaining_time":0.9075565394},
{"learn":[0.471019465],"iteration":623,"passed_time":1.501873152,"remaining_time":0.9049748479},
{"learn":[0.4705248839],"iteration":624,"passed_time":1.503856883,"remaining_time":0.9023141296},
{"learn":[0.4704694806],"iteration":625,"passed_time":1.505740789,"remaining_time":0.8995959347},
{"learn":[0.4702298506],"iteration":626,"passed_time":1.507795941,"remaining_time":0.8969822742},
{"learn":[0.4698655667],"iteration":627,"passed_time":1.509785297,"remaining_time":0.8943314181},
{"learn":[0.4696469796],"iteration":628,"passed_time":1.511544536,"remaining_time":0.8915469362},
{"learn":[0.469106175],"iteration":629,"passed_time":1.513609112,"remaining_time":0.8889450338},
{"learn":[0.4686110708],"iteration":630,"passed_time":1.515465616,"remaining_time":0.8862231571},
{"learn":[0.4684977491],"iteration":631,"passed_time":1.517161437,"remaining_time":0.8834104573},
{"learn":[0.4683960259],"iteration":632,"passed_time":1.518966548,"remaining_time":0.8806646493},
{"learn":[0.4679635469],"iteration":633,"passed_time":1.5209237,"remaining_time":0.8780095806},
{"learn":[0.4678203405],"iteration":634,"passed_time":1.522890357,"remaining_time":0.8753621738},
{"learn":[0.4673985407],"iteration":635,"passed_time":1.524779284,"remaining_time":0.8726724202},
{"learn":[0.4673138266],"iteration":636,"passed_time":1.526730768,"remaining_time":0.8700208304},
{"learn":[0.4668884999],"iteration":637,"passed_time":1.528551537,"remaining_time":0.8672972673},
{"learn":[0.4668106198],"iteration":638,"passed_time":1.53029801,"remaining_time":0.8645345563},
{"learn":[0.4665403977],"iteration":639,"passed_time":1.532234185,"remaining_time":0.8618817289},
{"learn":[0.4663466779],"iteration":640,"passed_time":1.53412743,"remaining_time":0.859207094},
{"learn":[0.4658495085],"iteration":641,"passed_time":1.535738468,"remaining_time":0.8563775258},
{"learn":[0.4654066379],"iteration":642,"passed_time":1.537778608,"remaining_time":0.853789989},
{"learn":[0.4647064097],"iteration":643,"passed_time":1.539551517,"remaining_time":0.8510564288},
{"learn":[0.4643364289],"iteration":644,"passed_time":1.541378576,"remaining_time":0.8483556505},
{"learn":[0.4637865606],"iteration":645,"passed_time":1.543346604,"remaining_time":0.8457348263},
{"learn":[0.4630682985],"iteration":646,"passed_time":1.545199306,"remaining_time":0.843053099},
{"learn":[0.4630479127],"iteration":647,"passed_time":1.546865753,"remaining_time":0.8402727548},
{"learn":[0.462708156],"iteration":648,"passed_time":1.548876558,"remaining_time":0.8376820832},
{"learn":[0.4626528117],"iteration":649,"passed_time":1.550665768,"remaining_time":0.8349738753},
{"learn":[0.4624631132],"iteration":650,"passed_time":1.552357915,"remaining_time":0.832216455},
{"learn":[0.4620269084],"iteration":651,"passed_time":1.554609276,"remaining_time":0.8297607792},
{"learn":[0.4615484422],"iteration":652,"passed_time":1.556458419,"remaining_time":0.8270919928},
{"learn":[0.4614888649],"iteration":653,"passed_time":1.558265279,"remaining_time":0.8244033434},
{"learn":[0.4613847635],"iteration":654,"passed_time":1.560164719,"remaining_time":0.8217661495},
{"learn":[0.4608129272],"iteration":655,"passed_time":1.561991332,"remaining_time":0.8190930155},
{"learn":[0.46050649],"iteration":656,"passed_time":1.563880189,"remaining_time":0.8164549539},
{"learn":[0.4604887355],"iteration":657,"passed_time":1.565782252,"remaining_time":0.8138260336},
{"learn":[0.460411474],"iteration":658,"passed_time":1.56769469,"remaining_time":0.8112046877},
{"learn":[0.4598131019],"iteration":659,"passed_time":1.569509993,"remaining_time":0.8085354511},
{"learn":[0.4590265225],"iteration":660,"passed_time":1.571231367,"remaining_time":0.8058206255},
{"learn":[0.4586383998],"iteration":661,"passed_time":1.573002244,"remaining_time":0.8031340761},
{"learn":[0.4581704932],"iteration":662,"passed_time":1.57492128,"remaining_time":0.8005255976},
{"learn":[0.4577215023],"iteration":663,"passed_time":1.576871227,"remaining_time":0.7979348379},
{"learn":[0.4571176647],"iteration":664,"passed_time":1.578870652,"remaining_time":0.79537093},
{"learn":[0.4561644645],"iteration":665,"passed_time":1.580695567,"remaining_time":0.7927212002},
{"learn":[0.4560482745],"iteration":666,"passed_time":1.582386743,"remaining_time":0.7900071744},
{"learn":[0.4559131558],"iteration":667,"passed_time":1.584131324,"remaining_time":0.7873227539},
{"learn":[0.455332841],"iteration":668,"passed_time":1.586142153,"remaining_time":0.7847728741},
{"learn":[0.454686861],"iteration":669,"passed_time":1.588016368,"remaining_time":0.7821573158},
{"learn":[0.4543309039],"iteration":670,"passed_time":1.589966099,"remaining_time":0.7795809933},
{"learn":[0.4538471232],"iteration":671,"passed_time":1.591894513,"remaining_time":0.7769961313},
{"learn":[0.4536883637],"iteration":672,"passed_time":1.593558935,"remaining_time":0.7742849504},
{"learn":[0.4531985644],"iteration":673,"passed_time":1.595394608,"remaining_time":0.7716597068},
{"learn":[0.4527765272],"iteration":674,"passed_time":1.597222501,"remaining_time":0.7690330562},
{"learn":[0.4525919016],"iteration":675,"passed_time":1.599049746,"remaining_time":0.7664084583},
{"learn":[0.4518712986],"iteration":676,"passed_time":1.600998081,"remaining_time":0.7638439882},
{"learn":[0.4512191202],"iteration":677,"passed_time":1.602898263,"remaining_time":0.7612584669},
{"learn":[0.4504868374],"iteration":678,"passed_time":1.604782476,"remaining_time":0.7586674151},
{"learn":[0.4503503759],"iteration":679,"passed_time":1.606605652,"remaining_time":0.7560497184},
{"learn":[0.4502082369],"iteration":680,"passed_time":1.608525944,"remaining_time":0.7534798476},
{"learn":[0.4498005061],"iteration":681,"passed_time":1.610448064,"remaining_time":0.7509127338},
{"learn":[0.4490286191],"iteration":682,"passed_time":1.612274913,"remaining_time":0.7483032903},
{"learn":[0.4489136312],"iteration":683,"passed_time":1.61429326,"remaining_time":0.7457846054},
{"learn":[0.4485567699],"iteration":684,"passed_time":1.616164416,"remaining_time":0.743199695},
{"learn":[0.4478500886],"iteration":685,"passed_time":1.6179734,"remaining_time":0.7405884074},
{"learn":[0.4474547789],"iteration":686,"passed_time":1.620086209,"remaining_time":0.7381178797},
{"learn":[0.4473052756],"iteration":687,"passed_time":1.621852892,"remaining_time":0.7354914276},
{"learn":[0.4468809885],"iteration":688,"passed_time":1.623650505,"remaining_time":0.7328814327},
{"learn":[0.4467144203],"iteration":689,"passed_time":1.62586059,"remaining_time":0.7304591058},
{"learn":[0.4462919483],"iteration":690,"passed_time":1.627704829,"remaining_time":0.7278737947},
{"learn":[0.4456122786],"iteration":691,"passed_time":1.629406359,"remaining_time":0.7252271077},
{"learn":[0.4452265549],"iteration":692,"passed_time":1.631393993,"remaining_time":0.7227098928},
{"learn":[0.4451259104],"iteration":693,"passed_time":1.633372345,"remaining_time":0.7201901116},
{"learn":[0.4446957202],"iteration":694,"passed_time":1.635213307,"remaining_time":0.7176115951},
{"learn":[0.4446666455],"iteration":695,"passed_time":1.637151337,"remaining_time":0.7150775953},
{"learn":[0.4441006023],"iteration":696,"passed_time":1.639052078,"remaining_time":0.7125290956},
{"learn":[0.4436583398],"iteration":697,"passed_time":1.640839837,"remaining_time":0.7099335685},
{"learn":[0.4433181904],"iteration":698,"passed_time":1.642671153,"remaining_time":0.7073591087},
{"learn":[0.4430288653],"iteration":699,"passed_time":1.644448127,"remaining_time":0.7047634831},
{"learn":[0.442281184],"iteration":700,"passed_time":1.646326726,"remaining_time":0.7022135393},
{"learn":[0.4419235586],"iteration":701,"passed_time":1.648107968,"remaining_time":0.69962418},
{"learn":[0.441784685],"iteration":702,"passed_time":1.649864755,"remaining_time":0.6970267882},
{"learn":[0.4410761529],"iteration":703,"passed_time":1.651844351,"remaining_time":0.6945254656},
{"learn":[0.4409313206],"iteration":704,"passed_time":1.653745402,"remaining_time":0.6919927568},
{"learn":[0.4399793219],"iteration":705,"passed_time":1.655701174,"remaining_time":0.6894846249},
{"learn":[0.4394968764],"iteration":706,"passed_time":1.657597463,"remaining_time":0.6869534042},
{"learn":[0.4392980197],"iteration":707,"passed_time":1.659492923,"remaining_time":0.6844236348},
{"learn":[0.4390035033],"iteration":708,"passed_time":1.66142473,"remaining_time":0.6819105731},
{"learn":[0.4388364036],"iteration":709,"passed_time":1.663255125,"remaining_time":0.6793577272},
{"learn":[0.4383536728],"iteration":710,"passed_time":1.665054644,"remaining_time":0.676794363},
{"learn":[0.4378048622],"iteration":711,"passed_time":1.667062214,"remaining_time":0.6743173},
{"learn":[0.4368680045],"iteration":712,"passed_time":1.668904571,"remaining_time":0.6717750516},
{"learn":[0.4363079529],"iteration":713,"passed_time":1.67064309,"remaining_time":0.6691931705},
{"learn":[0.4359464739],"iteration":714,"passed_time":1.672454612,"remaining_time":0.6666427473},
{"learn":[0.4357969068],"iteration":715,"passed_time":1.674399655,"remaining_time":0.6641473492},
{"learn":[0.4351070651],"iteration":716,"passed_time":1.676201581,"remaining_time":0.6615969977},
{"learn":[0.4350059821],"iteration":717,"passed_time":1.678119099,"remaining_time":0.6590941308},
{"learn":[0.4346922476],"iteration":718,"passed_time":1.680150349,"remaining_time":0.6566373407},
{"learn":[0.4346753107],"iteration":719,"passed_time":1.681925698,"remaining_time":0.6540822159},
{"learn":[0.4345272304],"iteration":720,"passed_time":1.68377973,"remaining_time":0.6515597012},
{"learn":[0.43398233],"iteration":721,"passed_time":1.685737726,"remaining_time":0.6490790692},
{"learn":[0.4336262758],"iteration":722,"passed_time":1.687502263,"remaining_time":0.6465257634},
{"learn":[0.4333497877],"iteration":723,"passed_time":1.689445265,"remaining_time":0.6440426701},
{"learn":[0.4331550572],"iteration":724,"passed_time":1.691363608,"remaining_time":0.6415517135},
{"learn":[0.4327776302],"iteration":725,"passed_time":1.693149708,"remaining_time":0.6390124243},
{"learn":[0.4323269081],"iteration":726,"passed_time":1.695154963,"remaining_time":0.6365575034},
{"learn":[0.4319590151],"iteration":727,"passed_time":1.697136146,"remaining_time":0.634094824},
{"learn":[0.4315529486],"iteration":728,"passed_time":1.698993227,"remaining_time":0.6315873313},
{"learn":[0.4311719034],"iteration":729,"passed_time":1.700914154,"remaining_time":0.629105235},
{"learn":[0.4308649018],"iteration":730,"passed_time":1.702911117,"remaining_time":0.6266526544},
{"learn":[0.4307576503],"iteration":731,"passed_time":1.704887108,"remaining_time":0.6241936407},
{"learn":[0.4305991747],"iteration":732,"passed_time":1.706633156,"remaining_time":0.6216521863},
{"learn":[0.4302064097],"iteration":733,"passed_time":1.70889379,"remaining_time":0.6192993843},
{"learn":[0.4298608321],"iteration":734,"passed_time":1.710825556,"remaining_time":0.6168282617},
{"learn":[0.4296852873],"iteration":735,"passed_time":1.712514725,"remaining_time":0.614271586},
{"learn":[0.4290120848],"iteration":736,"passed_time":1.714489745,"remaining_time":0.6118192711},
{"learn":[0.4289881595],"iteration":737,"passed_time":1.716367287,"remaining_time":0.6093336437},
{"learn":[0.4287300826],"iteration":738,"passed_time":1.718319672,"remaining_time":0.6068760951},
{"learn":[0.4285104422],"iteration":739,"passed_time":1.720086039,"remaining_time":0.6043545542},
{"learn":[0.4280370092],"iteration":740,"passed_time":1.722102096,"remaining_time":0.601922325},
{"learn":[0.4275579084],"iteration":741,"passed_time":1.723965264,"remaining_time":0.5994380567},
{"learn":[0.4271090987],"iteration":742,"passed_time":1.725670829,"remaining_time":0.5969009461},
{"learn":[0.4269101181],"iteration":743,"passed_time":1.727611437,"remaining_time":0.5944469462},
{"learn":[0.426720305],"iteration":744,"passed_time":1.729672744,"remaining_time":0.5920356373},
{"learn":[0.4265343739],"iteration":745,"passed_time":1.731440598,"remaining_time":0.589525351},
{"learn":[0.4259845837],"iteration":746,"passed_time":1.733379594,"remaining_time":0.5870750166},
{"learn":[0.4256857737],"iteration":747,"passed_time":1.735252985,"remaining_time":0.584603947},
{"learn":[0.4253942413],"iteration":748,"passed_time":1.7371276,"remaining_time":0.5821348832},
{"learn":[0.4250243225],"iteration":749,"passed_time":1.739464856,"remaining_time":0.5798216188},
{"learn":[0.424483454],"iteration":750,"passed_time":1.7412101,"remaining_time":0.5773120039},
{"learn":[0.4239500248],"iteration":751,"passed_time":1.743171464,"remaining_time":0.5748756956},
{"learn":[0.4231280211],"iteration":752,"passed_time":1.745083427,"remaining_time":0.5724244443},
{"learn":[0.4224342274],"iteration":753,"passed_time":1.746882011,"remaining_time":0.5699376322},
{"learn":[0.4222655075],"iteration":754,"passed_time":1.748740035,"remaining_time":0.567471932},
{"learn":[0.421620273],"iteration":755,"passed_time":1.750777592,"remaining_time":0.5650657837},
{"learn":[0.4211689753],"iteration":756,"passed_time":1.752948722,"remaining_time":0.5627034867},
{"learn":[0.420809444],"iteration":757,"passed_time":1.754748792,"remaining_time":0.5602232291},
{"learn":[0.4205571824],"iteration":758,"passed_time":1.75664088,"remaining_time":0.5577739816},
{"learn":[0.4204044823],"iteration":759,"passed_time":1.758652536,"remaining_time":0.5553639587},
{"learn":[0.4203776504],"iteration":760,"passed_time":1.760441442,"remaining_time":0.5528850259},
{"learn":[0.4199215351],"iteration":761,"passed_time":1.76224204,"remaining_time":0.5504115559},
{"learn":[0.4196450594],"iteration":762,"passed_time":1.764164676,"remaining_time":0.5479777564},
{"learn":[0.4189931081],"iteration":763,"passed_time":1.766158061,"remaining_time":0.5455671498},
{"learn":[0.4183685655],"iteration":764,"passed_time":1.767820304,"remaining_time":0.5430559103},
{"learn":[0.4179040288],"iteration":765,"passed_time":1.769839414,"remaining_time":0.5406559047},
{"learn":[0.4175026596],"iteration":766,"passed_time":1.771600933,"remaining_time":0.5381786407},
{"learn":[0.4170887615],"iteration":767,"passed_time":1.773400372,"remaining_time":0.5357146956},
{"learn":[0.4168224101],"iteration":768,"passed_time":1.775268464,"remaining_time":0.5332731017},
{"learn":[0.4166266926],"iteration":769,"passed_time":1.777245075,"remaining_time":0.5308654119},
{"learn":[0.4157404875],"iteration":770,"passed_time":1.779073286,"remaining_time":0.5284147633},
{"learn":[0.4148891617],"iteration":771,"passed_time":1.780938264,"remaining_time":0.5259765857},
{"learn":[0.4147376664],"iteration":772,"passed_time":1.782692568,"remaining_time":0.5235073906},
{"learn":[0.4143278465],"iteration":773,"passed_time":1.78445531,"remaining_time":0.5210425064},
{"learn":[0.4139574295],"iteration":774,"passed_time":1.786185436,"remaining_time":0.5185699652},
{"learn":[0.4134315905],"iteration":775,"passed_time":1.788124248,"remaining_time":0.5161595768},
{"learn":[0.412826256],"iteration":776,"passed_time":1.790056525,"remaining_time":0.5137485265},
{"learn":[0.4123849396],"iteration":777,"passed_time":1.791885364,"remaining_time":0.5113091912},
{"learn":[0.4114492551],"iteration":778,"passed_time":1.793876632,"remaining_time":0.5089175042},
{"learn":[0.4112848916],"iteration":779,"passed_time":1.795866001,"remaining_time":0.506526308},
{"learn":[0.4108334139],"iteration":780,"passed_time":1.797492559,"remaining_time":0.5040344052},
{"learn":[0.4099383192],"iteration":781,"passed_time":1.799750281,"remaining_time":0.5017206667},
{"learn":[0.4098962376],"iteration":782,"passed_time":1.801590182,"remaining_time":0.4992912765},
{"learn":[0.4093946612],"iteration":783,"passed_time":1.803351812,"remaining_time":0.4968418257},
{"learn":[0.4089135298],"iteration":784,"passed_time":1.805154337,"remaining_time":0.4944053279},
{"learn":[0.4085935438],"iteration":785,"passed_time":1.806982022,"remaining_time":0.4919772936},
{"learn":[0.4083488895],"iteration":786,"passed_time":1.808686762,"remaining_time":0.48951751},
{"learn":[0.4077288717],"iteration":787,"passed_time":1.810617588,"remaining_time":0.487120468},
{"learn":[0.4074423898],"iteration":788,"passed_time":1.812714089,"remaining_time":0.4847689136},
{"learn":[0.4070492518],"iteration":789,"passed_time":1.814777446,"remaining_time":0.4824091945},
{"learn":[0.4065890982],"iteration":790,"passed_time":1.81674106,"remaining_time":0.4800238704},
{"learn":[0.4062042382],"iteration":791,"passed_time":1.818548138,"remaining_time":0.4775985008},
{"learn":[0.4060193339],"iteration":792,"passed_time":1.820503981,"remaining_time":0.4752135233},
{"learn":[0.4056611472],"iteration":793,"passed_time":1.822244165,"remaining_time":0.472773675},
{"learn":[0.4049932636],"iteration":794,"passed_time":1.824320693,"remaining_time":0.4704223171},
{"learn":[0.404610272],"iteration":795,"passed_time":1.826100071,"remaining_time":0.4679954957},
{"learn":[0.4043157013],"iteration":796,"passed_time":1.827863425,"remaining_time":0.4655662175},
{"learn":[0.4042994517],"iteration":797,"passed_time":1.829762005,"remaining_time":0.4631728383},
{"learn":[0.4038692519],"iteration":798,"passed_time":1.831700102,"remaining_time":0.4607906388},
{"learn":[0.4035658403],"iteration":799,"passed_time":1.833613166,"remaining_time":0.4584032915},
{"learn":[0.4028607625],"iteration":800,"passed_time":1.835654115,"remaining_time":0.4560489001},
{"learn":[0.4022076771],"iteration":801,"passed_time":1.837691808,"remaining_time":0.4536944863},
{"learn":[0.4020716563],"iteration":802,"passed_time":1.839764514,"remaining_time":0.451349451},
{"learn":[0.4018074073],"iteration":803,"passed_time":1.841809937,"remaining_time":0.4489984424},
{"learn":[0.4015519379],"iteration":804,"passed_time":1.843860875,"remaining_time":0.4466495287},
{"learn":[0.400673293],"iteration":805,"passed_time":1.845733331,"remaining_time":0.4442583947},
{"learn":[0.4001994751],"iteration":806,"passed_time":1.84800217,"remaining_time":0.4419633443},
{"learn":[0.3999934508],"iteration":807,"passed_time":1.849955101,"remaining_time":0.4395932913},
{"learn":[0.3994050753],"iteration":808,"passed_time":1.851845763,"remaining_time":0.4372095682},
{"learn":[0.3992199067],"iteration":809,"passed_time":1.853914998,"remaining_time":0.4348689501},
{"learn":[0.398754376],"iteration":810,"passed_time":1.856115026,"remaining_time":0.432559482},
{"learn":[0.3982373414],"iteration":811,"passed_time":1.858153169,"remaining_time":0.4302128028},
{"learn":[0.3980239884],"iteration":812,"passed_time":1.8600315,"remaining_time":0.4278301236},
{"learn":[0.3977914059],"iteration":813,"passed_time":1.862154173,"remaining_time":0.4255045162},
{"learn":[0.3974679525],"iteration":814,"passed_time":1.864023434,"remaining_time":0.4231218837},
{"learn":[0.3969604523],"iteration":815,"passed_time":1.866250059,"remaining_time":0.4208210917},
{"learn":[0.3964843467],"iteration":816,"passed_time":1.868465069,"remaining_time":0.4185178795},
{"learn":[0.3963882134],"iteration":817,"passed_time":1.870344335,"remaining_time":0.416140182},
{"learn":[0.3960879214],"iteration":818,"passed_time":1.872273841,"remaining_time":0.413774805},
{"learn":[0.3958171616],"iteration":819,"passed_time":1.874236702,"remaining_time":0.4114178126},
{"learn":[0.3955321541],"iteration":820,"passed_time":1.87633495,"remaining_time":0.4090912985},
{"learn":[0.3950084135],"iteration":821,"passed_time":1.878277951,"remaining_time":0.4067317217},
{"learn":[0.3948160147],"iteration":822,"passed_time":1.880292146,"remaining_time":0.4043884689},
{"learn":[0.3944603899],"iteration":823,"passed_time":1.882280307,"remaining_time":0.4020404539},
{"learn":[0.3939351918],"iteration":824,"passed_time":1.884197679,"remaining_time":0.3996782955},
{"learn":[0.3936574386],"iteration":825,"passed_time":1.885963743,"remaining_time":0.3972853405},
{"learn":[0.3932122902],"iteration":826,"passed_time":1.888208901,"remaining_time":0.3949941231},
{"learn":[0.393039313],"iteration":827,"passed_time":1.890123727,"remaining_time":0.3926343974},
{"learn":[0.3924397901],"iteration":828,"passed_time":1.891931386,"remaining_time":0.3902536394},
{"learn":[0.3918038462],"iteration":829,"passed_time":1.89393214,"remaining_time":0.3879138119},
{"learn":[0.3915949667],"iteration":830,"passed_time":1.895983273,"remaining_time":0.3855850459},
{"learn":[0.3910574799],"iteration":831,"passed_time":1.898187104,"remaining_time":0.3832877806},
{"learn":[0.3907241667],"iteration":832,"passed_time":1.900039172,"remaining_time":0.3809202181},
{"learn":[0.390281845],"iteration":833,"passed_time":1.901948169,"remaining_time":0.378565223},
{"learn":[0.3902347405],"iteration":834,"passed_time":1.903884691,"remaining_time":0.3762167354},
{"learn":[0.3899503011],"iteration":835,"passed_time":1.905767876,"remaining_time":0.3738587699},
{"learn":[0.3896523437],"iteration":836,"passed_time":1.907764181,"remaining_time":0.3715239684},
{"learn":[0.3889499712],"iteration":837,"passed_time":1.90966879,"remaining_time":0.3691722481},
{"learn":[0.3886717601],"iteration":838,"passed_time":1.911566611,"remaining_time":0.3668202913},
{"learn":[0.3880455831],"iteration":839,"passed_time":1.913410773,"remaining_time":0.3644591949},
{"learn":[0.3878011713],"iteration":840,"passed_time":1.915600013,"remaining_time":0.3621645684},
{"learn":[0.3874574864],"iteration":841,"passed_time":1.917578091,"remaining_time":0.3598305682},
{"learn":[0.3869938811],"iteration":842,"passed_time":1.919452484,"remaining_time":0.3574781019},
{"learn":[0.3864105856],"iteration":843,"passed_time":1.921521306,"remaining_time":0.3551627059},
{"learn":[0.3859485484],"iteration":844,"passed_time":1.92361223,"remaining_time":0.3528519476},
{"learn":[0.3856856571],"iteration":845,"passed_time":1.925558552,"remaining_time":0.3505153864},
{"learn":[0.3854291991],"iteration":846,"passed_time":1.927585562,"remaining_time":0.3481943222},
{"learn":[0.3851651274],"iteration":847,"passed_time":1.929559986,"remaining_time":0.3458645258},
{"learn":[0.3846024514],"iteration":848,"passed_time":1.931327107,"remaining_time":0.3434986964},
{"learn":[0.3843596118],"iteration":849,"passed_time":1.933389943,"remaining_time":0.3411864605},
{"learn":[0.3840891798],"iteration":850,"passed_time":1.935226694,"remaining_time":0.338835226},
{"learn":[0.3836472419],"iteration":851,"passed_time":1.937187269,"remaining_time":0.3365067087},
{"learn":[0.3834601728],"iteration":852,"passed_time":1.939109672,"remaining_time":0.3341724757},
{"learn":[0.3827598557],"iteration":853,"passed_time":1.941035038,"remaining_time":0.3318397137},
{"learn":[0.3826234285],"iteration":854,"passed_time":1.942915112,"remaining_time":0.3295002236},
{"learn":[0.3822380583],"iteration":855,"passed_time":1.944911275,"remaining_time":0.327181336},
{"learn":[0.3820129366],"iteration":856,"passed_time":1.946969258,"remaining_time":0.3248735168},
{"learn":[0.381884589],"iteration":857,"passed_time":1.948770905,"remaining_time":0.3225238561},
{"learn":[0.3815927605],"iteration":858,"passed_time":1.950790195,"remaining_time":0.3202111962},
{"learn":[0.3811306611],"iteration":859,"passed_time":1.953019286,"remaining_time":0.3179333721},
{"learn":[0.3810922893],"iteration":860,"passed_time":1.954916121,"remaining_time":0.3156020219},
{"learn":[0.3808044772],"iteration":861,"passed_time":1.956810732,"remaining_time":0.3132713236},
{"learn":[0.3805779201],"iteration":862,"passed_time":1.958880707,"remaining_time":0.310969475},
{"learn":[0.3800312186],"iteration":863,"passed_time":1.960874103,"remaining_time":0.3086561087},
{"learn":[0.3798209248],"iteration":864,"passed_time":1.962909789,"remaining_time":0.3063500827},
{"learn":[0.3795030438],"iteration":865,"passed_time":1.965021031,"remaining_time":0.304056372},
{"learn":[0.3790733311],"iteration":866,"passed_time":1.967052235,"remaining_time":0.3017508042},
{"learn":[0.3786383511],"iteration":867,"passed_time":1.968959137,"remaining_time":0.2994269655},
{"learn":[0.3782988076],"iteration":868,"passed_time":1.971059265,"remaining_time":0.2971332149},
{"learn":[0.3780629909],"iteration":869,"passed_time":1.973381908,"remaining_time":0.2948731587},
{"learn":[0.3779309394],"iteration":870,"passed_time":1.975272759,"remaining_time":0.292549008},
{"learn":[0.3775924063],"iteration":871,"passed_time":1.977192371,"remaining_time":0.2902300729},
{"learn":[0.3773394288],"iteration":872,"passed_time":1.979114679,"remaining_time":0.2879124447},
{"learn":[0.3766843057],"iteration":873,"passed_time":1.98141617,"remaining_time":0.2856503861},
{"learn":[0.376629798],"iteration":874,"passed_time":1.983626612,"remaining_time":0.2833752303},
{"learn":[0.3762268566],"iteration":875,"passed_time":1.986025395,"remaining_time":0.2811268823},
{"learn":[0.3759631171],"iteration":876,"passed_time":1.988206464,"remaining_time":0.2788476568},
{"learn":[0.3754435371],"iteration":877,"passed_time":1.990228722,"remaining_time":0.2765465877},
{"learn":[0.3753892322],"iteration":878,"passed_time":1.992404776,"remaining_time":0.2742673241},
{"learn":[0.3750238486],"iteration":879,"passed_time":1.994462607,"remaining_time":0.2719721736},
{"learn":[0.3746711573],"iteration":880,"passed_time":1.996394705,"remaining_time":0.2696605787},
{"learn":[0.3743357191],"iteration":881,"passed_time":1.998423713,"remaining_time":0.2673628096},
{"learn":[0.3741036113],"iteration":882,"passed_time":2.000372921,"remaining_time":0.2650550756},
{"learn":[0.3737479757],"iteration":883,"passed_time":2.002273958,"remaining_time":0.2627418317},
{"learn":[0.3732522029],"iteration":884,"passed_time":2.004386859,"remaining_time":0.2604570494},
{"learn":[0.372894415],"iteration":885,"passed_time":2.007003488,"remaining_time":0.2582374691},
{"learn":[0.3723484623],"iteration":886,"passed_time":2.008938035,"remaining_time":0.2559300992},
{"learn":[0.3720157755],"iteration":887,"passed_time":2.011053816,"remaining_time":0.2536464272},
{"learn":[0.3714764855],"iteration":888,"passed_time":2.013359042,"remaining_time":0.2513867871},
{"learn":[0.3712941059],"iteration":889,"passed_time":2.015278249,"remaining_time":0.2490793342},
{"learn":[0.370662468],"iteration":890,"passed_time":2.017734412,"remaining_time":0.2468384409},
{"learn":[0.3704362427],"iteration":891,"passed_time":2.019918618,"remaining_time":0.2445641376},
{"learn":[0.3702721392],"iteration":892,"passed_time":2.021949122,"remaining_time":0.2422716193},
{"learn":[0.3699701601],"iteration":893,"passed_time":2.02408576,"remaining_time":0.2399922713},
{"learn":[0.3694575904],"iteration":894,"passed_time":2.026078476,"remaining_time":0.2376963575},
{"learn":[0.3692112857],"iteration":895,"passed_time":2.027963004,"remaining_time":0.235388563},
{"learn":[0.3685864414],"iteration":896,"passed_time":2.030585069,"remaining_time":0.2331664015},
{"learn":[0.3682856866],"iteration":897,"passed_time":2.032720296,"remaining_time":0.2308880514},
{"learn":[0.3679029484],"iteration":898,"passed_time":2.034695963,"remaining_time":0.2285920937},
{"learn":[0.3676872305],"iteration":899,"passed_time":2.036611968,"remaining_time":0.2262902187},
{"learn":[0.3672441239],"iteration":900,"passed_time":2.038524681,"remaining_time":0.2239888385},
{"learn":[0.3669746788],"iteration":901,"passed_time":2.040595357,"remaining_time":0.2217054823},
{"learn":[0.3665507274],"iteration":902,"passed_time":2.04251231,"remaining_time":0.2194060842},
{"learn":[0.3662585887],"iteration":903,"passed_time":2.044476192,"remaining_time":0.217112516},
{"learn":[0.3659068204],"iteration":904,"passed_time":2.046443694,"remaining_time":0.2148200563},
{"learn":[0.3654615103],"iteration":905,"passed_time":2.048521809,"remaining_time":0.2125397903},
{"learn":[0.3652787403],"iteration":906,"passed_time":2.050511506,"remaining_time":0.2102509042},
{"learn":[0.3649299902],"iteration":907,"passed_time":2.052336219,"remaining_time":0.2079459605},
{"learn":[0.364572779],"iteration":908,"passed_time":2.054427513,"remaining_time":0.2056687609},
{"learn":[0.3643084532],"iteration":909,"passed_time":2.056467628,"remaining_time":0.2033869082},
{"learn":[0.3641052091],"iteration":910,"passed_time":2.058651066,"remaining_time":0.2011195882},
{"learn":[0.3638746883],"iteration":911,"passed_time":2.060674698,"remaining_time":0.1988370322},
{"learn":[0.3634066176],"iteration":912,"passed_time":2.062679219,"remaining_time":0.1965532224},
{"learn":[0.3630689049],"iteration":913,"passed_time":2.064717003,"remaining_time":0.1942731534},
{"learn":[0.362572961],"iteration":914,"passed_time":2.066878768,"remaining_time":0.1920051314},
{"learn":[0.3624583324],"iteration":915,"passed_time":2.068849996,"remaining_time":0.1897198687},
{"learn":[0.3624386497],"iteration":916,"passed_time":2.070923352,"remaining_time":0.1874445346},
{"learn":[0.3620935673],"iteration":917,"passed_time":2.072968099,"remaining_time":0.1851670851},
{"learn":[0.3618440273],"iteration":918,"passed_time":2.074903542,"remaining_time":0.182880508},
{"learn":[0.3616954159],"iteration":919,"passed_time":2.076844854,"remaining_time":0.1805952047},
{"learn":[0.3614188852],"iteration":920,"passed_time":2.078795276,"remaining_time":0.1783114298},
{"learn":[0.3612182132],"iteration":921,"passed_time":2.080997346,"remaining_time":0.176049667},
{"learn":[0.3607223184],"iteration":922,"passed_time":2.083035323,"remaining_time":0.1737743444},
{"learn":[0.3602176137],"iteration":923,"passed_time":2.085196466,"remaining_time":0.1715096661},
{"learn":[0.3598559815],"iteration":924,"passed_time":2.08718849,"remaining_time":0.1692314992},
{"learn":[0.3596833294],"iteration":925,"passed_time":2.0892183,"remaining_time":0.16695697},
{"learn":[0.3592452606],"iteration":926,"passed_time":2.091279104,"remaining_time":0.1646854095},
{"learn":[0.3589511809],"iteration":927,"passed_time":2.093446729,"remaining_time":0.1624225911},
{"learn":[0.3586955455],"iteration":928,"passed_time":2.095643949,"remaining_time":0.1601622394},
{"learn":[0.3582662955],"iteration":929,"passed_time":2.097632413,"remaining_time":0.1578863106},
{"learn":[0.3578397465],"iteration":930,"passed_time":2.099836497,"remaining_time":0.1556269799},
{"learn":[0.3576505429],"iteration":931,"passed_time":2.101957179,"remaining_time":0.1533616826},
{"learn":[0.3573562533],"iteration":932,"passed_time":2.104203267,"remaining_time":0.1511057009},
{"learn":[0.3568952779],"iteration":933,"passed_time":2.106420739,"remaining_time":0.1488477181},
{"learn":[0.3560850617],"iteration":934,"passed_time":2.108533725,"remaining_time":0.1465825584},
{"learn":[0.3558935211],"iteration":935,"passed_time":2.110570681,"remaining_time":0.1443125252},
{"learn":[0.3555325063],"iteration":936,"passed_time":2.112795392,"remaining_time":0.1420556133},
{"learn":[0.3552156592],"iteration":937,"passed_time":2.114801265,"remaining_time":0.1397843054},
{"learn":[0.3550276992],"iteration":938,"passed_time":2.116715311,"remaining_time":0.1375075974},
{"learn":[0.3547294273],"iteration":939,"passed_time":2.118904874,"remaining_time":0.1352492473},
{"learn":[0.3543420129],"iteration":940,"passed_time":2.120933744,"remaining_time":0.132980968},
{"learn":[0.3541208618],"iteration":941,"passed_time":2.122959106,"remaining_time":0.130712981},
{"learn":[0.3538909572],"iteration":942,"passed_time":2.125103366,"remaining_time":0.1284526955},
{"learn":[0.3537246419],"iteration":943,"passed_time":2.127142834,"remaining_time":0.1261864393},
{"learn":[0.3533742575],"iteration":944,"passed_time":2.129309327,"remaining_time":0.1239280561},
{"learn":[0.3530952613],"iteration":945,"passed_time":2.131173405,"remaining_time":0.1216526045},
{"learn":[0.3527807035],"iteration":946,"passed_time":2.133505439,"remaining_time":0.1194042115},
{"learn":[0.3524571229],"iteration":947,"passed_time":2.135655303,"remaining_time":0.1171456496},
{"learn":[0.3523659057],"iteration":948,"passed_time":2.137628943,"remaining_time":0.1148778463},
{"learn":[0.3521872025],"iteration":949,"passed_time":2.139771697,"remaining_time":0.112619563},
{"learn":[0.3519074051],"iteration":950,"passed_time":2.141680873,"remaining_time":0.1103494877},
{"learn":[0.3515767697],"iteration":951,"passed_time":2.143810058,"remaining_time":0.1080912634},
{"learn":[0.3512677231],"iteration":952,"passed_time":2.146191587,"remaining_time":0.1058457551},
{"learn":[0.3507565093],"iteration":953,"passed_time":2.148699212,"remaining_time":0.1036060417},
{"learn":[0.3506523736],"iteration":954,"passed_time":2.150792132,"remaining_time":0.1013462261},
{"learn":[0.3500841858],"iteration":955,"passed_time":2.15278325,"remaining_time":0.09908207429},
{"learn":[0.3498352508],"iteration":956,"passed_time":2.156121874,"remaining_time":0.09687903929},
{"learn":[0.3492644563],"iteration":957,"passed_time":2.15850284,"remaining_time":0.0946316485},
{"learn":[0.3489722409],"iteration":958,"passed_time":2.160568153,"remaining_time":0.09237048414},
{"learn":[0.3487829534],"iteration":959,"passed_time":2.162952514,"remaining_time":0.0901230214},
{"learn":[0.3485361992],"iteration":960,"passed_time":2.165137006,"remaining_time":0.08786716257},
{"learn":[0.3482205452],"iteration":961,"passed_time":2.167322988,"remaining_time":0.08561151095},
{"learn":[0.3479234415],"iteration":962,"passed_time":2.169228369,"remaining_time":0.08334522291},
{"learn":[0.3476701407],"iteration":963,"passed_time":2.171785574,"remaining_time":0.08110402557},
{"learn":[0.3472813469],"iteration":964,"passed_time":2.174262277,"remaining_time":0.07885925358},
{"learn":[0.3470771976],"iteration":965,"passed_time":2.176203987,"remaining_time":0.07659517138},
{"learn":[0.3468288178],"iteration":966,"passed_time":2.178294904,"remaining_time":0.0743368478},
{"learn":[0.3465636911],"iteration":967,"passed_time":2.18064073,"remaining_time":0.07208729687},
{"learn":[0.3462594777],"iteration":968,"passed_time":2.182675038,"remaining_time":0.06982758121},
{"learn":[0.3461441346],"iteration":969,"passed_time":2.18464481,"remaining_time":0.06756633432},
{"learn":[0.3457915025],"iteration":970,"passed_time":2.186480645,"remaining_time":0.06530168766},
{"learn":[0.3456577618],"iteration":971,"passed_time":2.188413044,"remaining_time":0.06304070497},
{"learn":[0.3452251032],"iteration":972,"passed_time":2.190351121,"remaining_time":0.06078055525},
{"learn":[0.3451059516],"iteration":973,"passed_time":2.192358625,"remaining_time":0.05852292017},
{"learn":[0.3446856201],"iteration":974,"passed_time":2.19410496,"remaining_time":0.05625910155},
{"learn":[0.3446604871],"iteration":975,"passed_time":2.196028067,"remaining_time":0.05400069017},
{"learn":[0.3446288968],"iteration":976,"passed_time":2.197814,"remaining_time":0.05173973594},
{"learn":[0.3444551024],"iteration":977,"passed_time":2.199744776,"remaining_time":0.04948301133},
{"learn":[0.3440179876],"iteration":978,"passed_time":2.20175533,"remaining_time":0.04722866387},
{"learn":[0.3438449393],"iteration":979,"passed_time":2.203769427,"remaining_time":0.04497488626},
{"learn":[0.3436121878],"iteration":980,"passed_time":2.20573877,"remaining_time":0.0427207305},
{"learn":[0.3432746787],"iteration":981,"passed_time":2.207770769,"remaining_time":0.04046830331},
{"learn":[0.3431843783],"iteration":982,"passed_time":2.20973092,"remaining_time":0.03821508203},
{"learn":[0.3426193253],"iteration":983,"passed_time":2.211707723,"remaining_time":0.0359627272},
{"learn":[0.3421280378],"iteration":984,"passed_time":2.213707926,"remaining_time":0.03371128822},
{"learn":[0.342028087],"iteration":985,"passed_time":2.215599852,"remaining_time":0.03145882143},
{"learn":[0.3418109026],"iteration":986,"passed_time":2.217513271,"remaining_time":0.02920736831},
{"learn":[0.3414899062],"iteration":987,"passed_time":2.219288986,"remaining_time":0.02695492696},
{"learn":[0.3412026015],"iteration":988,"passed_time":2.22125524,"remaining_time":0.02470556889},
{"learn":[0.3407504258],"iteration":989,"passed_time":2.223404259,"remaining_time":0.02245862888},
{"learn":[0.3405481054],"iteration":990,"passed_time":2.225319862,"remaining_time":0.02020976665},
{"learn":[0.3402889963],"iteration":991,"passed_time":2.227244469,"remaining_time":0.01796164894},
{"learn":[0.3401909443],"iteration":992,"passed_time":2.229130677,"remaining_time":0.01571391212},
{"learn":[0.3397844368],"iteration":993,"passed_time":2.231080648,"remaining_time":0.01346728761},
{"learn":[0.3392907424],"iteration":994,"passed_time":2.233045942,"remaining_time":0.01122133639},
{"learn":[0.3391554684],"iteration":995,"passed_time":2.235013955,"remaining_time":0.008975959659},
{"learn":[0.3386205305],"iteration":996,"passed_time":2.236803086,"remaining_time":0.006730601062},
{"learn":[0.3385507884],"iteration":997,"passed_time":2.238793987,"remaining_time":0.004486561096},
{"learn":[0.3383089725],"iteration":998,"passed_time":2.240750664,"remaining_time":0.002242993658},
{"learn":[0.3379779526],"iteration":999,"passed_time":2.242687648,"remaining_time":0}
]}